{"quattroporte": {"gen": {"Price": "Rs. 1.71 Crores onwards", "Engine": " 2987 to 3799 cc", "Transmission": " Automatic", "FuelType": " Diesel and Petrol", "Seating Capacity": " 5"}, "detail": {"Base ": {"key Specifications": {"Price": "Rs. 1.71 Crores", "Engine": " 2987 cc", "Transmission": " Automatic", "FuelType": " Diesel", "Seating Capacity": " 5"}, "spec": {"Engine & Transmission": {"Engine": "2987cc, 6 Cylinders In V Shape, 4 Valves/Cylinder, DOHC ", "Engine Type": "Tubro Diesel ", "Fuel Type ": "Diesel ", "Max Power (bhp@rpm)": "275 bhp @ 4000 rpm ", "Max Torque (Nm@rpm)": "600 Nm @ 2000 rpm ", "Drivetrain": "RWD ", "Transmission": "Automatic - 8 Gears, Conventional + Paddle Shift, Sport Mode ", "Turbocharger / Supercharger": "Yes, Fixed Geometry ", "Others": "Engine Start-Stop Function "}, "Dimensions & Weight": {"Length": "5262 mm", "Width": "1948 mm", "Height": "1481 mm", "Wheelbase": "3171 mm"}, "Capacity": {"Doors": "4 Doors", "Seating Capacity": "5 Person", "No of Seating Rows": "2 Rows", "Bootspace": "450 litres", "Fuel Tank Capacity": "90 litres"}, "Suspensions, Brakes & Steering ": {"Suspension Front": "double wishbone suspension with forged aluminium arms & hubs ", "Suspension Rear": "double wishbone suspension with forged aluminium arms & hubs ", "Front Brake Type": "Disc ", "Rear Brake Type": "Disc ", "Minimum Turning Radius": "6.15 metres", "Steering Type": "Power assisted (Electric) ", "Wheels": "Alloy Wheels ", "Spare Wheel": "Alloy ", "Front Tyres": "\r\n\t\t\t\t\t\t\t\t\t\t\t\t\t\t\t\t\t245 / 40 R19 \r\n\t\t\t\t\t\t\t\t\t\t\t\t\t\t\t\t\t\t View all tyres\n", "Rear Tyres": "285 / 35 R19 "}}, "fea": {"Safety": {"Airbags": "6 Airbags  ", "Dual-Stage Airbags": "Yes  ", "Middle Rear Head Rest": "Yes  ", "Tyre Pressure Monitoring System (TPMS)": "Yes  ", "Child Seat Anchor Points": "Yes  ", "Seat Belt Warning": "Yes  "}, "Braking & Traction": {"Anti-Lock Braking System (ABS)": "Yes  ", "Electronic Brake-force Distribution (EBD)": "Yes  ", "Brake Assist (BA)": "Yes  ", "Electronic Stability Program (ESP)": "Yes  ", "Hill Hold Control": "Yes  ", "Traction Control System (TC/TCS)": "Yes  ", "Ride Height Adjustment": "Yes  ", "Hill Descent Control": "Yes  ", "Limited Slip Differential (LSD)": "Yes  ", "Differential Lock": "Electronic  "}, "Locks & Security": {"Engine immobilizer": "Yes  ", "Central Locking": "Remote  ", "Speed Sensing Door Lock": "Yes  ", "Child Safety Lock": "Yes  "}, "Comfort & Convenience": {"Air Conditioner": "Automatic Climate Control  ", "Rear AC": "Vents Only  ", "12V Power Outlets": "Yes  ", "Steering Adjustment": "Tilt & Telescopic  ", "Headlight off and lgnition Key Off Reminder": "Yes  ", "Cruise Control": "Yes  ", "Parking Sensors": "Front & Rear  ", "Parking Assist": "Reverse Camera with Guidance  ", "Anti-glare Mirrors": "Electronic - All  ", "Cabin-Boot Access": "Yes  ", "Vanity Mirrors on Sun Visors": "Driver & Co-Driver  ", "Heater": "Yes  "}, "Seats & Upholstery": {"Seat Upholstery": "Leather  ", "Leather-wrapped Steering Wheel": "Yes  ", "Leather-wrapped Gear Knob": "Yes  ", "Driver Seat Adjustment": "Electrically Adjustable with Memory Function  ", "Front Passenger Seat Adjustment": "Electrically Adjustable with Memory Function  ", "Lumbar Support": "Driver & Co-Driver  ", "Adjustable Lumbar Support": "Electric - 2 way  ", "Driver Armrest": "Yes  ", "Rear Passenger Seats": "Bench  ", "Rear Passenger Adjustable seats": "Electrically Adjustable with Memory Function  ", "Ventilated Seats": "All  ", "Ventilated Seat Type": "Heated  ", "Interiors": "Single Tone  ", "Rear Armrest": "Yes  ", "Folding Rear Seat": "Full  ", "Split Rear Seat": "60:40 split  ", "Front Seat Pockets": "Yes  ", "Adjustable Head-rests": "Front & Rear  ", "Electrically Adjustable Headrests": "Front & Rear  ", "Head-rests": "Front & Rear  "}, "Storage": {"Cup Holders": "Front & Rear  ", "Driver Armrest Storage": "Yes  ", "Cooled Glove Box ": "Yes  ", "Sunglass Holder": "Yes  "}, "Doors, Windows, Mirrors & Wipers": {"Power Windows": "Front & Rear  ", "One Touch -Down": "All  ", "One Touch - Up": "All  ", "Adjustable ORVM": "Electrically Adjustable & Retractable  ", "Turn Indicators on ORVM": "Yes  ", "Rear Defogger": "Yes  ", "Exterior Door Handles": "Body Coloured  ", "Rain-sensing Wipers": "Yes  ", "Interior Door Handles": "Chrome  ", "Door Blinds": "Rear - electric  ", "Boot-lid Opener": "Internal with Remote  ", "Rear Window Blind": "Electric  ", "Outside Rear View Mirrors (ORVMs)": "Body Coloured  "}, "Exterior": {"Sunroof / Moonroof": "Electro-Transparent Panoramic Sunroof  ", "Roof Mounted Antenna": "Yes  ", "Body-Coloured  Bumpers ": "Yes  ", "Chrome Finish Exhaust pipe": "Yes  "}, "Lighting": {"Headlights": "LED  ", "Automatic Head Lamps": "Yes  ", "Follow me home headlamps": "Yes  ", "Fog Lamps": "Front  ", "Tail Lights": "LED  ", "Cabin Lamps": "Centre  ", "Headlight Height Adjuster": "Yes  ", "Glove Box Lamp": "Yes  ", "Lights on Vanity Mirrors": "Driver & Co-Driver  ", "Rear Reading Lamp": "Yes  ", "Cornering Headlights": "Active  "}, "Instrumentation": {"Instrument Cluster": "Analog  ", "Trip Meter": "2 Trips  ", "Average Fuel Consumption": "Yes  ", "Average Speed": "Yes  ", "Distance to Empty": "Yes  ", "Clock": "Digital  ", "Low Fuel Level Warning": "Yes  ", "Door Ajar Warning": "Yes  ", "Adjustable Cluster Brightness": "Yes  ", "Gear Indicator": "Yes  ", "Shift Indicator": "Yes  ", "Heads Up Display (HUD)": "Yes  ", "Tachometer": "Analog  ", "Instantaneous Consumption": "Yes  "}, "Entertainment, Information & Communication": {"Integrated (in-dash) Music System": "Yes  ", "Head Unit Size": "2 Din  ", "Display": "Touch-screen Display  ", "GPS Navigation System": "Yes  ", "Speakers": "6+  ", "USB Compatibility": "Yes  ", "Aux Compatibility": "Yes  ", "Bluetooth Compatibility": "Phone  ", "MP3 Playback": "Yes  ", "CD Player": "Yes  ", "AM/FM Radio": "Yes  ", "iPod Compatibility": "Yes  ", "Steering mounted controls": "Yes  ", "Voice Command": "Yes  "}, "Manufacturer Warranty": {"Warranty (Years)": "3  ", "Warranty (Kilometres)": "Unlimited  "}}}, "Gran Lusso ": {"key Specifications": {"Price": "Rs. 1.78 Crores", "Engine": " 2987 cc", "Transmission": " Automatic", "FuelType": " Diesel", "Seating Capacity": " 5"}, "spec": {"Engine & Transmission": {"Engine": "2987cc, 6 Cylinders In V Shape, 4 Valves/Cylinder, DOHC ", "Engine Type": "Tubro Diesel ", "Fuel Type ": "Diesel ", "Max Power (bhp@rpm)": "275 bhp @ 4000 rpm ", "Max Torque (Nm@rpm)": "600 Nm @ 2000 rpm ", "Drivetrain": "RWD ", "Transmission": "Automatic - 8 Gears, Conventional + Paddle Shift, Sport Mode ", "Turbocharger / Supercharger": "Yes, Fixed Geometry ", "Others": "Engine Start-Stop Function "}, "Dimensions & Weight": {"Length": "5262 mm", "Width": "1948 mm", "Height": "1481 mm", "Wheelbase": "3171 mm"}, "Capacity": {"Doors": "4 Doors", "Seating Capacity": "5 Person", "No of Seating Rows": "2 Rows", "Bootspace": "450 litres", "Fuel Tank Capacity": "90 litres"}, "Suspensions, Brakes & Steering ": {"Suspension Front": "double wishbone suspension with forged aluminium arms & hubs ", "Suspension Rear": "double wishbone suspension with forged aluminium arms & hubs ", "Front Brake Type": "Disc ", "Rear Brake Type": "Disc ", "Minimum Turning Radius": "6.15 metres", "Steering Type": "Power assisted (Electric) ", "Wheels": "Alloy Wheels ", "Spare Wheel": "Alloy ", "Front Tyres": "\r\n\t\t\t\t\t\t\t\t\t\t\t\t\t\t\t\t\t245 / 40 R19 \r\n\t\t\t\t\t\t\t\t\t\t\t\t\t\t\t\t", "Rear Tyres": "285 / 35 R20 "}}, "fea": {"Safety": {"Airbags": "6 Airbags  ", "Dual-Stage Airbags": "Yes  ", "Middle Rear Head Rest": "Yes  ", "Tyre Pressure Monitoring System (TPMS)": "Yes  ", "Child Seat Anchor Points": "Yes  ", "Seat Belt Warning": "Yes  "}, "Braking & Traction": {"Anti-Lock Braking System (ABS)": "Yes  ", "Electronic Brake-force Distribution (EBD)": "Yes  ", "Brake Assist (BA)": "Yes  ", "Electronic Stability Program (ESP)": "Yes  ", "Hill Hold Control": "Yes  ", "Traction Control System (TC/TCS)": "Yes  ", "Ride Height Adjustment": "Yes  ", "Hill Descent Control": "Yes  ", "Limited Slip Differential (LSD)": "Yes  ", "Differential Lock": "Electronic  "}, "Locks & Security": {"Engine immobilizer": "Yes  ", "Central Locking": "Remote  ", "Speed Sensing Door Lock": "Yes  ", "Child Safety Lock": "Yes  "}, "Comfort & Convenience": {"Air Conditioner": "Automatic Climate Control  ", "Rear AC": "Vents Only  ", "12V Power Outlets": "Yes  ", "Steering Adjustment": "Tilt & Telescopic  ", "Headlight off and lgnition Key Off Reminder": "Yes  ", "Cruise Control": "Yes  ", "Parking Sensors": "Front & Rear  ", "Parking Assist": "Reverse Camera with Guidance  ", "Anti-glare Mirrors": "Electronic - All  ", "Cabin-Boot Access": "Yes  ", "Vanity Mirrors on Sun Visors": "Driver & Co-Driver  ", "Heater": "Yes  "}, "Seats & Upholstery": {"Seat Upholstery": "Leather  ", "Leather-wrapped Steering Wheel": "Yes  ", "Leather-wrapped Gear Knob": "Yes  ", "Driver Seat Adjustment": "Electrically Adjustable with Memory Function  ", "Front Passenger Seat Adjustment": "Electrically Adjustable with Memory Function  ", "Lumbar Support": "Driver & Co-Driver  ", "Adjustable Lumbar Support": "Electric - 2 way  ", "Driver Armrest": "Yes  ", "Rear Passenger Seats": "Bench  ", "Rear Passenger Adjustable seats": "Electrically Adjustable with Memory Function  ", "Ventilated Seats": "All  ", "Ventilated Seat Type": "Heated  ", "Interiors": "Single Tone  ", "Rear Armrest": "Yes  ", "Folding Rear Seat": "Full  ", "Split Rear Seat": "60:40 split  ", "Front Seat Pockets": "Yes  ", "Adjustable Head-rests": "Front & Rear  ", "Electrically Adjustable Headrests": "Front & Rear  ", "Head-rests": "Front & Rear  "}, "Storage": {"Cup Holders": "Front & Rear  ", "Driver Armrest Storage": "Yes  ", "Cooled Glove Box ": "Yes  ", "Sunglass Holder": "Yes  "}, "Doors, Windows, Mirrors & Wipers": {"Power Windows": "Front & Rear  ", "One Touch -Down": "All  ", "One Touch - Up": "All  ", "Adjustable ORVM": "Electrically Adjustable & Retractable  ", "Turn Indicators on ORVM": "Yes  ", "Rear Defogger": "Yes  ", "Exterior Door Handles": "Body Coloured  ", "Rain-sensing Wipers": "Yes  ", "Interior Door Handles": "Chrome  ", "Door Blinds": "Rear - electric  ", "Boot-lid Opener": "Internal with Remote  ", "Rear Window Blind": "Electric  ", "Outside Rear View Mirrors (ORVMs)": "Body Coloured  "}, "Exterior": {"Sunroof / Moonroof": "Electro-Transparent Panoramic Sunroof  ", "Roof Mounted Antenna": "Yes  ", "Body-Coloured  Bumpers ": "Yes  ", "Chrome Finish Exhaust pipe": "Yes  "}, "Lighting": {"Headlights": "LED  ", "Automatic Head Lamps": "Yes  ", "Follow me home headlamps": "Yes  ", "Fog Lamps": "Front  ", "Tail Lights": "LED  ", "Cabin Lamps": "Centre  ", "Headlight Height Adjuster": "Yes  ", "Glove Box Lamp": "Yes  ", "Lights on Vanity Mirrors": "Driver & Co-Driver  ", "Rear Reading Lamp": "Yes  ", "Cornering Headlights": "Active  "}, "Instrumentation": {"Instrument Cluster": "Analog  ", "Trip Meter": "2 Trips  ", "Average Fuel Consumption": "Yes  ", "Average Speed": "Yes  ", "Distance to Empty": "Yes  ", "Clock": "Digital  ", "Low Fuel Level Warning": "Yes  ", "Door Ajar Warning": "Yes  ", "Adjustable Cluster Brightness": "Yes  ", "Gear Indicator": "Yes  ", "Shift Indicator": "Yes  ", "Heads Up Display (HUD)": "Yes  ", "Tachometer": "Analog  ", "Instantaneous Consumption": "Yes  "}, "Entertainment, Information & Communication": {"Integrated (in-dash) Music System": "Yes  ", "Head Unit Size": "2 Din  ", "Display": "Touch-screen Display  ", "GPS Navigation System": "Yes  ", "Speakers": "6+  ", "USB Compatibility": "Yes  ", "Aux Compatibility": "Yes  ", "Bluetooth Compatibility": "Phone  ", "MP3 Playback": "Yes  ", "CD Player": "Yes  ", "AM/FM Radio": "Yes  ", "iPod Compatibility": "Yes  ", "Steering mounted controls": "Yes  ", "Voice Command": "Yes  "}, "Manufacturer Warranty": {"Warranty (Years)": "3  ", "Warranty (Kilometres)": "Unlimited  "}}}, "Gran Sport ": {"key Specifications": {"Price": "Rs. 1.83 Crores", "Engine": " 2987 cc", "Transmission": " Automatic", "FuelType": " Diesel", "Seating Capacity": " 5"}, "spec": {"Engine & Transmission": {"Engine": "2987cc, 6 Cylinders In V Shape, 4 Valves/Cylinder, DOHC ", "Engine Type": "Tubro Diesel ", "Fuel Type ": "Diesel ", "Max Power (bhp@rpm)": "275 bhp @ 4000 rpm ", "Max Torque (Nm@rpm)": "600 Nm @ 2000 rpm ", "Drivetrain": "RWD ", "Transmission": "Automatic - 8 Gears, Conventional + Paddle Shift, Sport Mode ", "Turbocharger / Supercharger": "Yes, Fixed Geometry ", "Others": "Engine Start-Stop Function "}, "Dimensions & Weight": {"Length": "5262 mm", "Width": "1948 mm", "Height": "1481 mm", "Wheelbase": "3171 mm"}, "Capacity": {"Doors": "4 Doors", "Seating Capacity": "5 Person", "No of Seating Rows": "2 Rows", "Bootspace": "450 litres", "Fuel Tank Capacity": "90 litres"}, "Suspensions, Brakes & Steering ": {"Suspension Front": "double wishbone suspension with forged aluminium arms & hubs ", "Suspension Rear": "double wishbone suspension with forged aluminium arms & hubs ", "Front Brake Type": "Disc ", "Rear Brake Type": "Disc ", "Minimum Turning Radius": "6.15 metres", "Steering Type": "Power assisted (Electric) ", "Wheels": "Alloy Wheels ", "Spare Wheel": "Alloy ", "Front Tyres": "\r\n\t\t\t\t\t\t\t\t\t\t\t\t\t\t\t\t\t245 / 40 R19 \r\n\t\t\t\t\t\t\t\t\t\t\t\t\t\t\t\t", "Rear Tyres": "285 / 35 R21 "}}, "fea": {"Safety": {"Airbags": "6 Airbags  ", "Dual-Stage Airbags": "Yes  ", "Middle Rear Head Rest": "Yes  ", "Tyre Pressure Monitoring System (TPMS)": "Yes  ", "Child Seat Anchor Points": "Yes  ", "Seat Belt Warning": "Yes  "}, "Braking & Traction": {"Anti-Lock Braking System (ABS)": "Yes  ", "Electronic Brake-force Distribution (EBD)": "Yes  ", "Brake Assist (BA)": "Yes  ", "Electronic Stability Program (ESP)": "Yes  ", "Hill Hold Control": "Yes  ", "Traction Control System (TC/TCS)": "Yes  ", "Ride Height Adjustment": "Yes  ", "Hill Descent Control": "Yes  ", "Limited Slip Differential (LSD)": "Yes  ", "Differential Lock": "Electronic  "}, "Locks & Security": {"Engine immobilizer": "Yes  ", "Central Locking": "Remote  ", "Speed Sensing Door Lock": "Yes  ", "Child Safety Lock": "Yes  "}, "Comfort & Convenience": {"Air Conditioner": "Automatic Climate Control  ", "Rear AC": "Vents Only  ", "12V Power Outlets": "Yes  ", "Steering Adjustment": "Tilt & Telescopic  ", "Headlight off and lgnition Key Off Reminder": "Yes  ", "Cruise Control": "Yes  ", "Parking Sensors": "Front & Rear  ", "Parking Assist": "Reverse Camera with Guidance  ", "Anti-glare Mirrors": "Electronic - All  ", "Cabin-Boot Access": "Yes  ", "Vanity Mirrors on Sun Visors": "Driver & Co-Driver  ", "Heater": "Yes  "}, "Seats & Upholstery": {"Seat Upholstery": "Leather  ", "Leather-wrapped Steering Wheel": "Yes  ", "Leather-wrapped Gear Knob": "Yes  ", "Driver Seat Adjustment": "Electrically Adjustable with Memory Function  ", "Front Passenger Seat Adjustment": "Electrically Adjustable with Memory Function  ", "Lumbar Support": "Driver & Co-Driver  ", "Adjustable Lumbar Support": "Electric - 2 way  ", "Driver Armrest": "Yes  ", "Rear Passenger Seats": "Bench  ", "Rear Passenger Adjustable seats": "Electrically Adjustable with Memory Function  ", "Ventilated Seats": "All  ", "Ventilated Seat Type": "Heated  ", "Interiors": "Single Tone  ", "Rear Armrest": "Yes  ", "Folding Rear Seat": "Full  ", "Split Rear Seat": "60:40 split  ", "Front Seat Pockets": "Yes  ", "Adjustable Head-rests": "Front & Rear  ", "Electrically Adjustable Headrests": "Front & Rear  ", "Head-rests": "Front & Rear  "}, "Storage": {"Cup Holders": "Front & Rear  ", "Driver Armrest Storage": "Yes  ", "Cooled Glove Box ": "Yes  ", "Sunglass Holder": "Yes  "}, "Doors, Windows, Mirrors & Wipers": {"Power Windows": "Front & Rear  ", "One Touch -Down": "All  ", "One Touch - Up": "All  ", "Adjustable ORVM": "Electrically Adjustable & Retractable  ", "Turn Indicators on ORVM": "Yes  ", "Rear Defogger": "Yes  ", "Exterior Door Handles": "Body Coloured  ", "Rain-sensing Wipers": "Yes  ", "Interior Door Handles": "Chrome  ", "Door Blinds": "Rear - electric  ", "Boot-lid Opener": "Internal with Remote  ", "Rear Window Blind": "Electric  ", "Outside Rear View Mirrors (ORVMs)": "Body Coloured  "}, "Exterior": {"Sunroof / Moonroof": "Electro-Transparent Panoramic Sunroof  ", "Roof Mounted Antenna": "Yes  ", "Body-Coloured  Bumpers ": "Yes  ", "Chrome Finish Exhaust pipe": "Yes  "}, "Lighting": {"Headlights": "LED  ", "Automatic Head Lamps": "Yes  ", "Follow me home headlamps": "Yes  ", "Fog Lamps": "Front  ", "Tail Lights": "LED  ", "Cabin Lamps": "Centre  ", "Headlight Height Adjuster": "Yes  ", "Glove Box Lamp": "Yes  ", "Lights on Vanity Mirrors": "Driver & Co-Driver  ", "Rear Reading Lamp": "Yes  ", "Cornering Headlights": "Active  "}, "Instrumentation": {"Instrument Cluster": "Analog  ", "Trip Meter": "2 Trips  ", "Average Fuel Consumption": "Yes  ", "Average Speed": "Yes  ", "Distance to Empty": "Yes  ", "Clock": "Digital  ", "Low Fuel Level Warning": "Yes  ", "Door Ajar Warning": "Yes  ", "Adjustable Cluster Brightness": "Yes  ", "Gear Indicator": "Yes  ", "Shift Indicator": "Yes  ", "Heads Up Display (HUD)": "Yes  ", "Tachometer": "Analog  ", "Instantaneous Consumption": "Yes  "}, "Entertainment, Information & Communication": {"Integrated (in-dash) Music System": "Yes  ", "Head Unit Size": "2 Din  ", "Display": "Touch-screen Display  ", "GPS Navigation System": "Yes  ", "Speakers": "6+  ", "USB Compatibility": "Yes  ", "Aux Compatibility": "Yes  ", "Bluetooth Compatibility": "Phone  ", "MP3 Playback": "Yes  ", "CD Player": "Yes  ", "AM/FM Radio": "Yes  ", "iPod Compatibility": "Yes  ", "Steering mounted controls": "Yes  ", "Voice Command": "Yes  "}, "Manufacturer Warranty": {"Warranty (Years)": "3  ", "Warranty (Kilometres)": "Unlimited  "}}}, "GTS Gran Sport ": {"key Specifications": {"Price": "Rs. 2.56 Crores", "Engine": " 3799 cc", "Transmission": " Automatic", "FuelType": " Petrol", "Seating Capacity": " 5"}, "spec": {"Engine & Transmission": {"Engine": "3799cc, 8 Cylinders In V Shape, 4 Valves/Cylinder, DOHC ", "Engine Type": "Petrol V8 ", "Fuel Type ": "Petrol ", "Max Power (bhp@rpm)": "530 bhp @ 6500 rpm ", "Max Torque (Nm@rpm)": "710 Nm @ 2250 rpm ", "Drivetrain": "RWD ", "Transmission": "Automatic - 8 Gears, Conventional + Paddle Shift, Sport Mode ", "Turbocharger / Supercharger": "Yes, Fixed Geometry ", "Others": "Engine Start-Stop Function "}, "Dimensions & Weight": {"Length": "5262 mm", "Width": "1948 mm", "Height": "1481 mm", "Wheelbase": "3171 mm"}, "Capacity": {"Doors": "4 Doors", "Seating Capacity": "5 Person", "No of Seating Rows": "2 Rows", "Bootspace": "450 litres", "Fuel Tank Capacity": "90 litres"}, "Suspensions, Brakes & Steering ": {"Suspension Front": "double wishbone suspension with forged aluminium arms & hubs ", "Suspension Rear": "double wishbone suspension with forged aluminium arms & hubs ", "Front Brake Type": "Disc ", "Rear Brake Type": "Disc ", "Minimum Turning Radius": "6.15 metres", "Steering Type": "Power assisted (Electric) ", "Wheels": "Alloy Wheels ", "Spare Wheel": "Alloy ", "Front Tyres": "\r\n\t\t\t\t\t\t\t\t\t\t\t\t\t\t\t\t\t245 / 40 R19 \r\n\t\t\t\t\t\t\t\t\t\t\t\t\t\t\t\t", "Rear Tyres": "285 / 35 R21 "}}, "fea": {"Safety": {"Airbags": "6 Airbags  ", "Dual-Stage Airbags": "Yes  ", "Middle Rear Head Rest": "Yes  ", "Tyre Pressure Monitoring System (TPMS)": "Yes  ", "Child Seat Anchor Points": "Yes  ", "Seat Belt Warning": "Yes  "}, "Braking & Traction": {"Anti-Lock Braking System (ABS)": "Yes  ", "Electronic Brake-force Distribution (EBD)": "Yes  ", "Brake Assist (BA)": "Yes  ", "Electronic Stability Program (ESP)": "Yes  ", "Hill Hold Control": "Yes  ", "Traction Control System (TC/TCS)": "Yes  ", "Ride Height Adjustment": "Yes  ", "Hill Descent Control": "Yes  ", "Limited Slip Differential (LSD)": "Yes  ", "Differential Lock": "Electronic  "}, "Locks & Security": {"Engine immobilizer": "Yes  ", "Central Locking": "Remote  ", "Speed Sensing Door Lock": "Yes  ", "Child Safety Lock": "Yes  "}, "Comfort & Convenience": {"Air Conditioner": "Automatic Climate Control  ", "Rear AC": "Vents Only  ", "12V Power Outlets": "Yes  ", "Steering Adjustment": "Tilt & Telescopic  ", "Headlight off and lgnition Key Off Reminder": "Yes  ", "Cruise Control": "Yes  ", "Parking Sensors": "Front & Rear  ", "Parking Assist": "Reverse Camera with Guidance  ", "Anti-glare Mirrors": "Electronic - All  ", "Cabin-Boot Access": "Yes  ", "Vanity Mirrors on Sun Visors": "Driver & Co-Driver  ", "Heater": "Yes  "}, "Seats & Upholstery": {"Seat Upholstery": "Leather  ", "Leather-wrapped Steering Wheel": "Yes  ", "Leather-wrapped Gear Knob": "Yes  ", "Driver Seat Adjustment": "Electrically Adjustable with Memory Function  ", "Front Passenger Seat Adjustment": "Electrically Adjustable with Memory Function  ", "Lumbar Support": "Driver & Co-Driver  ", "Adjustable Lumbar Support": "Electric - 2 way  ", "Driver Armrest": "Yes  ", "Rear Passenger Seats": "Bench  ", "Rear Passenger Adjustable seats": "Electrically Adjustable with Memory Function  ", "Ventilated Seats": "All  ", "Ventilated Seat Type": "Heated  ", "Interiors": "Single Tone  ", "Rear Armrest": "Yes  ", "Folding Rear Seat": "Full  ", "Split Rear Seat": "60:40 split  ", "Front Seat Pockets": "Yes  ", "Adjustable Head-rests": "Front & Rear  ", "Electrically Adjustable Headrests": "Front & Rear  ", "Head-rests": "Front & Rear  "}, "Storage": {"Cup Holders": "Front & Rear  ", "Driver Armrest Storage": "Yes  ", "Cooled Glove Box ": "Yes  ", "Sunglass Holder": "Yes  "}, "Doors, Windows, Mirrors & Wipers": {"Power Windows": "Front & Rear  ", "One Touch -Down": "All  ", "One Touch - Up": "All  ", "Adjustable ORVM": "Electrically Adjustable & Retractable  ", "Turn Indicators on ORVM": "Yes  ", "Rear Defogger": "Yes  ", "Exterior Door Handles": "Body Coloured  ", "Rain-sensing Wipers": "Yes  ", "Interior Door Handles": "Chrome  ", "Door Blinds": "Rear - electric  ", "Boot-lid Opener": "Internal with Remote  ", "Rear Window Blind": "Electric  ", "Outside Rear View Mirrors (ORVMs)": "Body Coloured  "}, "Exterior": {"Sunroof / Moonroof": "Electro-Transparent Panoramic Sunroof  ", "Roof Mounted Antenna": "Yes  ", "Body-Coloured  Bumpers ": "Yes  ", "Chrome Finish Exhaust pipe": "Yes  "}, "Lighting": {"Headlights": "LED  ", "Automatic Head Lamps": "Yes  ", "Follow me home headlamps": "Yes  ", "Fog Lamps": "Front  ", "Tail Lights": "LED  ", "Cabin Lamps": "Centre  ", "Headlight Height Adjuster": "Yes  ", "Glove Box Lamp": "Yes  ", "Lights on Vanity Mirrors": "Driver & Co-Driver  ", "Rear Reading Lamp": "Yes  ", "Cornering Headlights": "Active  "}, "Instrumentation": {"Instrument Cluster": "TFT  ", "Trip Meter": "2 Trips  ", "Average Fuel Consumption": "Yes  ", "Average Speed": "Yes  ", "Distance to Empty": "Yes  ", "Clock": "Digital  ", "Low Fuel Level Warning": "Yes  ", "Door Ajar Warning": "Yes  ", "Adjustable Cluster Brightness": "Yes  ", "Gear Indicator": "Yes  ", "Shift Indicator": "Yes  ", "Heads Up Display (HUD)": "Yes  ", "Tachometer": "Analog  ", "Instantaneous Consumption": "Yes  "}, "Entertainment, Information & Communication": {"Integrated (in-dash) Music System": "Yes  ", "Head Unit Size": "2 Din  ", "Display": "Touch-screen Display  ", "GPS Navigation System": "Yes  ", "Speakers": "6+  ", "USB Compatibility": "Yes  ", "Aux Compatibility": "Yes  ", "Bluetooth Compatibility": "Phone  ", "MP3 Playback": "Yes  ", "CD Player": "Yes  ", "AM/FM Radio": "Yes  ", "iPod Compatibility": "Yes  ", "Steering mounted controls": "Yes  ", "Voice Command": "Yes  "}, "Manufacturer Warranty": {"Warranty (Years)": "3  ", "Warranty (Kilometres)": "Unlimited  "}}}, "GTS Gran Lusso ": {"key Specifications": {"Price": "Rs. 2.58 Crores", "Engine": " 3799 cc", "Transmission": " Automatic", "FuelType": " Petrol", "Seating Capacity": " 5"}, "spec": {"Engine & Transmission": {"Engine": "3799cc, 8 Cylinders In V Shape, 4 Valves/Cylinder, DOHC ", "Engine Type": "Petrol V8 ", "Fuel Type ": "Petrol ", "Max Power (bhp@rpm)": "530 bhp @ 6500 rpm ", "Max Torque (Nm@rpm)": "710 Nm @ 2250 rpm ", "Drivetrain": "RWD ", "Transmission": "Automatic - 8 Gears, Conventional + Paddle Shift, Sport Mode ", "Turbocharger / Supercharger": "Yes, Fixed Geometry ", "Others": "Engine Start-Stop Function "}, "Dimensions & Weight": {"Length": "5262 mm", "Width": "1948 mm", "Height": "1481 mm", "Wheelbase": "3171 mm"}, "Capacity": {"Doors": "4 Doors", "Seating Capacity": "5 Person", "No of Seating Rows": "2 Rows", "Bootspace": "450 litres", "Fuel Tank Capacity": "90 litres"}, "Suspensions, Brakes & Steering ": {"Suspension Front": "double wishbone suspension with forged aluminium arms & hubs ", "Suspension Rear": "double wishbone suspension with forged aluminium arms & hubs ", "Front Brake Type": "Disc ", "Rear Brake Type": "Disc ", "Minimum Turning Radius": "6.15 metres", "Steering Type": "Power assisted (Electric) ", "Wheels": "Alloy Wheels ", "Spare Wheel": "Alloy ", "Front Tyres": "\r\n\t\t\t\t\t\t\t\t\t\t\t\t\t\t\t\t\t245 / 40 R19 \r\n\t\t\t\t\t\t\t\t\t\t\t\t\t\t\t\t\t\t View all tyres\n", "Rear Tyres": "285 / 35 R20 "}}, "fea": {"Safety": {"Airbags": "6 Airbags  ", "Dual-Stage Airbags": "Yes  ", "Middle Rear Head Rest": "Yes  ", "Tyre Pressure Monitoring System (TPMS)": "Yes  ", "Child Seat Anchor Points": "Yes  ", "Seat Belt Warning": "Yes  "}, "Braking & Traction": {"Anti-Lock Braking System (ABS)": "Yes  ", "Electronic Brake-force Distribution (EBD)": "Yes  ", "Brake Assist (BA)": "Yes  ", "Electronic Stability Program (ESP)": "Yes  ", "Hill Hold Control": "Yes  ", "Traction Control System (TC/TCS)": "Yes  ", "Ride Height Adjustment": "Yes  ", "Hill Descent Control": "Yes  ", "Limited Slip Differential (LSD)": "Yes  ", "Differential Lock": "Electronic  "}, "Locks & Security": {"Engine immobilizer": "Yes  ", "Central Locking": "Remote  ", "Speed Sensing Door Lock": "Yes  ", "Child Safety Lock": "Yes  "}, "Comfort & Convenience": {"Air Conditioner": "Automatic Climate Control  ", "Rear AC": "Vents Only  ", "12V Power Outlets": "Yes  ", "Steering Adjustment": "Tilt & Telescopic  ", "Headlight off and lgnition Key Off Reminder": "Yes  ", "Cruise Control": "Yes  ", "Parking Sensors": "Front & Rear  ", "Parking Assist": "Reverse Camera with Guidance  ", "Anti-glare Mirrors": "Electronic - All  ", "Cabin-Boot Access": "Yes  ", "Vanity Mirrors on Sun Visors": "Driver & Co-Driver  ", "Heater": "Yes  "}, "Seats & Upholstery": {"Seat Upholstery": "Leather  ", "Leather-wrapped Steering Wheel": "Yes  ", "Leather-wrapped Gear Knob": "Yes  ", "Driver Seat Adjustment": "Electrically Adjustable with Memory Function  ", "Driver Power Seat Adjustment": "12  ", "Front Passenger Seat Adjustment": "Electrically Adjustable with Memory Function  ", "Front Passenger Power Seat Adjustment": "8  ", "Lumbar Support": "Driver & Co-Driver  ", "Adjustable Lumbar Support": "Electric - 2 way  ", "Driver Armrest": "Yes  ", "Rear Passenger Seats": "Bench  ", "Rear Passenger Adjustable seats": "Electrically Adjustable with Memory Function  ", "Rear Passenger Power Seat Adjustment": "4  ", "Ventilated Seats": "All  ", "Ventilated Seat Type": "Heated  ", "Interiors": "Single Tone  ", "Rear Armrest": "Yes  ", "Folding Rear Seat": "Full  ", "Split Rear Seat": "60:40 split  ", "Front Seat Pockets": "Yes  ", "Adjustable Head-rests": "Front & Rear  ", "Electrically Adjustable Headrests": "Front & Rear  ", "Head-rests": "Front & Rear  "}, "Storage": {"Cup Holders": "Front & Rear  ", "Driver Armrest Storage": "Yes  ", "Cooled Glove Box ": "Yes  ", "Sunglass Holder": "Yes  "}, "Doors, Windows, Mirrors & Wipers": {"Power Windows": "Front & Rear  ", "One Touch -Down": "All  ", "One Touch - Up": "All  ", "Adjustable ORVM": "Electrically Adjustable & Retractable  ", "Turn Indicators on ORVM": "Yes  ", "Rear Defogger": "Yes  ", "Exterior Door Handles": "Body Coloured  ", "Rain-sensing Wipers": "Yes  ", "Interior Door Handles": "Chrome  ", "Door Blinds": "Rear - electric  ", "Boot-lid Opener": "Internal with Remote  ", "Rear Window Blind": "Electric  ", "Outside Rear View Mirrors (ORVMs)": "Body Coloured  "}, "Exterior": {"Sunroof / Moonroof": "Electro-Transparent Panoramic Sunroof  ", "Roof Mounted Antenna": "Yes  ", "Body-Coloured  Bumpers ": "Yes  ", "Chrome Finish Exhaust pipe": "Yes  "}, "Lighting": {"Headlights": "LED  ", "Automatic Head Lamps": "Yes  ", "Follow me home headlamps": "Yes  ", "Fog Lamps": "Front  ", "Tail Lights": "LED  ", "Cabin Lamps": "Centre  ", "Headlight Height Adjuster": "Yes  ", "Glove Box Lamp": "Yes  ", "Lights on Vanity Mirrors": "Driver & Co-Driver  ", "Rear Reading Lamp": "Yes  ", "Cornering Headlights": "Active  "}, "Instrumentation": {"Instrument Cluster": "TFT  ", "Trip Meter": "2 Trips  ", "Average Fuel Consumption": "Yes  ", "Average Speed": "Yes  ", "Distance to Empty": "Yes  ", "Clock": "Digital  ", "Low Fuel Level Warning": "Yes  ", "Door Ajar Warning": "Yes  ", "Adjustable Cluster Brightness": "Yes  ", "Gear Indicator": "Yes  ", "Shift Indicator": "Yes  ", "Heads Up Display (HUD)": "Yes  ", "Tachometer": "Analog  ", "Instantaneous Consumption": "Yes  "}, "Entertainment, Information & Communication": {"Integrated (in-dash) Music System": "Yes  ", "Head Unit Size": "2 Din  ", "Display": "Touch-screen Display  ", "GPS Navigation System": "Yes  ", "Speakers": "6+  ", "USB Compatibility": "Yes  ", "Aux Compatibility": "Yes  ", "Bluetooth Compatibility": "Phone  ", "MP3 Playback": "Yes  ", "CD Player": "Yes  ", "AM/FM Radio": "Yes  ", "iPod Compatibility": "Yes  ", "Steering mounted controls": "Yes  ", "Voice Command": "Yes  "}, "Manufacturer Warranty": {"Warranty (Years)": "3  ", "Warranty (Kilometres)": "Unlimited  "}}}}}, "ghibli": {"gen": {"Price": "Rs. 1.38 Crores onwards", "Mileage": " 16.9 kmpl", "Engine": " 2987 cc", "Transmission": " Automatic", "FuelType": " Diesel"}, "detail": {"Diesel ": {"key Specifications": {"Price": "Rs. 1.38 Crores", "Mileage": " 16.9 kmpl", "Engine": " 2987 cc", "Transmission": " Automatic", "FuelType": " Diesel"}, "spec": {"Engine & Transmission": {"Engine": "2987cc, 6 Cylinders In V Shape, 4 Valves/Cylinder, DOHC ", "Engine Type": "Turbocharged Diesel Engine ", "Fuel Type ": "Diesel ", "Max Power (bhp@rpm)": "275 bhp @ 4000 rpm ", "Max Torque (Nm@rpm)": "600 Nm @ 2000 rpm ", "Mileage (ARAI)": "16.9 kmpl", "Drivetrain": "RWD ", "Transmission": "Automatic - 8 Gears, Conventional + Paddle Shift, Sport Mode ", "Turbocharger / Supercharger": "Turbocharged, Fixed Geometry ", "Others": "Engine Start-Stop Function "}, "Dimensions & Weight": {"Length": "4971 mm", "Width": "1945 mm", "Height": "1461 mm", "Wheelbase": "2998 mm", "Kerb Weight": "1835 kg"}, "Capacity": {"Doors": "4 Doors", "Seating Capacity": "5 Person", "No of Seating Rows": "2 Rows", "Bootspace": "500 litres", "Fuel Tank Capacity": "70 litres"}, "Suspensions, Brakes & Steering ": {"Suspension Front": "McPherson Strut Independent suspension ", "Suspension Rear": "Independent suspension ", "Front Brake Type": "Disc ", "Rear Brake Type": "Disc ", "Minimum Turning Radius": "5.85 metres", "Steering Type": "Power assisted (Electric) ", "Wheels": "Alloy Wheels ", "Spare Wheel": "Alloy ", "Front Tyres": "\r\n\t\t\t\t\t\t\t\t\t\t\t\t\t\t\t\t\t50 / 235 R18 \r\n\t\t\t\t\t\t\t\t\t\t\t\t\t\t\t\t", "Rear Tyres": "50 / 235 R18 "}}, "fea": {"Safety": {"Airbags": "7 Airbags  ", "Dual-Stage Airbags": "Yes  ", "Middle rear three-point seatbelt": "Yes  ", "Middle Rear Head Rest": "Yes  ", "Tyre Pressure Monitoring System (TPMS)": "Yes  ", "Child Seat Anchor Points": "Yes  ", "Seat Belt Warning": "Yes  "}, "Braking & Traction": {"Anti-Lock Braking System (ABS)": "Yes  ", "Electronic Brake-force Distribution (EBD)": "Yes  ", "Brake Assist (BA)": "Yes  ", "Electronic Stability Program (ESP)": "Yes  ", "Hill Hold Control": "Yes  ", "Traction Control System (TC/TCS)": "Yes  ", "Ride Height Adjustment": "Yes  ", "Hill Descent Control": "Yes  ", "Limited Slip Differential (LSD)": "Yes  ", "Differential Lock": "Electronic  "}, "Locks & Security": {"Engine immobilizer": "Yes  ", "Central Locking": "Keyless  ", "Speed Sensing Door Lock": "Yes  ", "Child Safety Lock": "Yes  "}, "Comfort & Convenience": {"Air Conditioner": "Automatic - Three Zone  ", "Rear AC": "Blower  ", "12V Power Outlets": "2  ", "Steering Adjustment": "Electric Tilt & Telescopic  ", "Headlight off and lgnition Key Off Reminder": "Yes  ", "Cruise Control": "Yes  ", "Parking Sensors": "Front & Rear  ", "Parking Assist": "Reverse Camera with Guidance  ", "Anti-glare Mirrors": "Electronic - All  ", "Cabin-Boot Access": "Yes  ", "Vanity Mirrors on Sun Visors": "Driver & Co-Driver  ", "Heater": "Yes  "}, "Seats & Upholstery": {"Seat Upholstery": "Leather  ", "Leather-wrapped Steering Wheel": "Yes  ", "Leather-wrapped Gear Knob": "Yes  ", "Driver Seat Adjustment": "Electrically Adjustable with Memory Function  ", "Front Passenger Seat Adjustment": "Electrically Adjustable with Memory Function  ", "Lumbar Support": "Driver & Co-Driver  ", "Adjustable Lumbar Support": "Electric - 4 way  ", "Driver Armrest": "Yes  ", "Rear Passenger Seats": "Bench  ", "Rear Passenger Adjustable seats": "Electrically Adjustable with Memory Function  ", "Ventilated Seats": "All  ", "Ventilated Seat Type": "Heated and cooled  ", "Interiors": "Single Tone  ", "Rear Armrest": "With Cup Holder  ", "Split Rear Seat": "60:40 split  ", "Front Seat Pockets": "Yes  ", "Adjustable Head-rests": "Front & Rear  ", "Electrically Adjustable Headrests": "Front & Rear  ", "Head-rests": "Front & Rear  "}, "Storage": {"Cup Holders": "Front & Rear  ", "Driver Armrest Storage": "Yes  ", "Cooled Glove Box ": "Yes  ", "Sunglass Holder": "Yes  "}, "Doors, Windows, Mirrors & Wipers": {"Power Windows": "Front & Rear  ", "One Touch -Down": "All  ", "One Touch - Up": "All  ", "Adjustable ORVM": "Electrically Adjustable & Retractable  ", "Turn Indicators on ORVM": "Yes  ", "Rear Defogger": "Yes  ", "Exterior Door Handles": "Body Coloured  ", "Rain-sensing Wipers": "Yes  ", "Interior Door Handles": "Chrome  ", "Door Pockets": "Front & Rear  ", "Door Blinds": "Rear - electric  ", "Boot-lid Opener": "Internal with Remote  ", "Rear Window Blind": "Electric  ", "Outside Rear View Mirrors (ORVMs)": "Body Coloured  "}, "Exterior": {"Sunroof / Moonroof": "Electrically Adjustable  ", "Roof Mounted Antenna": "Yes  ", "Body-Coloured  Bumpers ": "Yes  ", "Chrome Finish Exhaust pipe": "Yes  "}, "Lighting": {"Headlights": "LED  ", "Automatic Head Lamps": "Yes  ", "Follow me home headlamps": "Yes  ", "Fog Lamps": "Front  ", "Tail Lights": "LED  ", "Cabin Lamps": "Front and Rear  ", "Glove Box Lamp": "Yes  ", "Lights on Vanity Mirrors": "Driver & Co-Driver  ", "Rear Reading Lamp": "Yes  ", "Cornering Headlights": "Active  "}, "Instrumentation": {"Instrument Cluster": "Digital  ", "Trip Meter": "Electronic 2 Trips  ", "Average Fuel Consumption": "Yes  ", "Average Speed": "Yes  ", "Distance to Empty": "Yes  ", "Clock": "Digital  ", "Low Fuel Level Warning": "Yes  ", "Door Ajar Warning": "Yes  ", "Adjustable Cluster Brightness": "Yes  ", "Gear Indicator": "Yes  ", "Shift Indicator": "Yes  ", "Heads Up Display (HUD)": "Yes  ", "Tachometer": "Digital  ", "Instantaneous Consumption": "Yes  "}, "Entertainment, Information & Communication": {"Integrated (in-dash) Music System": "Yes  ", "Head Unit Size": "2 Din  ", "Display": "Touch-screen Display  ", "GPS Navigation System": "Yes  ", "Speakers": "6+  ", "USB Compatibility": "Yes  ", "Aux Compatibility": "Yes  ", "Bluetooth Compatibility": "Phone & Audio Streaming  ", "MP3 Playback": "Yes  ", "CD Player": "Yes  ", "DVD Playback": "Yes  ", "AM/FM Radio": "Yes  ", "iPod Compatibility": "Yes  ", "Internal Hard-drive": "Yes  ", "Steering mounted controls": "Yes  ", "Voice Command": "Yes  "}, "Manufacturer Warranty": {"Warranty (Years)": "3  ", "Warranty (Kilometres)": "Unlimited  "}}}, "GranSport ": {"key Specifications": {"Price": "Rs. 1.43 Crores", "Mileage": " 16.9 kmpl", "Engine": " 2987 cc", "Transmission": " Automatic", "FuelType": " Diesel"}, "spec": {"Engine & Transmission": {"Engine": "2987cc, 6 Cylinders In V Shape, 4 Valves/Cylinder, DOHC ", "Engine Type": "Turbocharged Diesel Engine ", "Fuel Type ": "Diesel ", "Max Power (bhp@rpm)": "275 bhp @ 4000 rpm ", "Max Torque (Nm@rpm)": "600 Nm @ 2000 rpm ", "Mileage (ARAI)": "16.9 kmpl", "Drivetrain": "RWD ", "Transmission": "Automatic - 8 Gears, Conventional + Paddle Shift, Sport Mode ", "Turbocharger / Supercharger": "Turbocharged, Fixed Geometry ", "Others": "Engine Start-Stop Function "}, "Dimensions & Weight": {"Length": "4971 mm", "Width": "1945 mm", "Height": "1461 mm", "Wheelbase": "2998 mm", "Kerb Weight": "1835 kg"}, "Capacity": {"Doors": "4 Doors", "Seating Capacity": "5 Person", "No of Seating Rows": "2 Rows", "Bootspace": "500 litres", "Fuel Tank Capacity": "70 litres"}, "Suspensions, Brakes & Steering ": {"Suspension Front": "McPherson Strut Independent suspension ", "Suspension Rear": "Independent suspension ", "Front Brake Type": "Disc ", "Rear Brake Type": "Disc ", "Minimum Turning Radius": "5.85 metres", "Steering Type": "Power assisted (Electric) ", "Wheels": "Alloy Wheels ", "Spare Wheel": "Alloy ", "Front Tyres": "\r\n\t\t\t\t\t\t\t\t\t\t\t\t\t\t\t\t\t50 / 235 R18 \r\n\t\t\t\t\t\t\t\t\t\t\t\t\t\t\t\t", "Rear Tyres": "50 / 235 R18 "}}, "fea": {"Safety": {"Airbags": "7 Airbags  ", "Dual-Stage Airbags": "Yes  ", "Middle rear three-point seatbelt": "Yes  ", "Middle Rear Head Rest": "Yes  ", "Tyre Pressure Monitoring System (TPMS)": "Yes  ", "Child Seat Anchor Points": "Yes  ", "Seat Belt Warning": "Yes  "}, "Braking & Traction": {"Anti-Lock Braking System (ABS)": "Yes  ", "Electronic Brake-force Distribution (EBD)": "Yes  ", "Brake Assist (BA)": "Yes  ", "Electronic Stability Program (ESP)": "Yes  ", "Hill Hold Control": "Yes  ", "Traction Control System (TC/TCS)": "Yes  ", "Ride Height Adjustment": "Yes  ", "Hill Descent Control": "Yes  ", "Limited Slip Differential (LSD)": "Yes  ", "Differential Lock": "Electronic  "}, "Locks & Security": {"Engine immobilizer": "Yes  ", "Central Locking": "Keyless  ", "Speed Sensing Door Lock": "Yes  ", "Child Safety Lock": "Yes  "}, "Comfort & Convenience": {"Air Conditioner": "Automatic - Three Zone  ", "Rear AC": "Blower  ", "12V Power Outlets": "2  ", "Steering Adjustment": "Electric Tilt & Telescopic  ", "Headlight off and lgnition Key Off Reminder": "Yes  ", "Cruise Control": "Yes  ", "Parking Sensors": "Front & Rear  ", "Parking Assist": "Reverse Camera with Guidance  ", "Anti-glare Mirrors": "Electronic - All  ", "Cabin-Boot Access": "Yes  ", "Vanity Mirrors on Sun Visors": "Driver & Co-Driver  ", "Heater": "Yes  "}, "Seats & Upholstery": {"Seat Upholstery": "Leather  ", "Leather-wrapped Steering Wheel": "Yes  ", "Leather-wrapped Gear Knob": "Yes  ", "Driver Seat Adjustment": "Electrically Adjustable with Memory Function  ", "Front Passenger Seat Adjustment": "Electrically Adjustable with Memory Function  ", "Lumbar Support": "Driver & Co-Driver  ", "Adjustable Lumbar Support": "Electric - 4 way  ", "Driver Armrest": "Yes  ", "Rear Passenger Seats": "Bench  ", "Rear Passenger Adjustable seats": "Electrically Adjustable with Memory Function  ", "Ventilated Seats": "All  ", "Ventilated Seat Type": "Heated and cooled  ", "Interiors": "Single Tone  ", "Rear Armrest": "With Cup Holder  ", "Split Rear Seat": "60:40 split  ", "Front Seat Pockets": "Yes  ", "Adjustable Head-rests": "Front & Rear  ", "Electrically Adjustable Headrests": "Front & Rear  ", "Head-rests": "Front & Rear  "}, "Storage": {"Cup Holders": "Front & Rear  ", "Driver Armrest Storage": "Yes  ", "Cooled Glove Box ": "Yes  ", "Sunglass Holder": "Yes  "}, "Doors, Windows, Mirrors & Wipers": {"Power Windows": "Front & Rear  ", "One Touch -Down": "All  ", "One Touch - Up": "All  ", "Adjustable ORVM": "Electrically Adjustable & Retractable  ", "Turn Indicators on ORVM": "Yes  ", "Rear Defogger": "Yes  ", "Exterior Door Handles": "Body Coloured  ", "Rain-sensing Wipers": "Yes  ", "Interior Door Handles": "Chrome  ", "Door Pockets": "Front & Rear  ", "Door Blinds": "Rear - electric  ", "Boot-lid Opener": "Internal with Remote  ", "Rear Window Blind": "Electric  ", "Outside Rear View Mirrors (ORVMs)": "Body Coloured  "}, "Exterior": {"Sunroof / Moonroof": "Electrically Adjustable  ", "Roof Mounted Antenna": "Yes  ", "Body-Coloured  Bumpers ": "Yes  ", "Chrome Finish Exhaust pipe": "Yes  "}, "Lighting": {"Headlights": "LED  ", "Automatic Head Lamps": "Yes  ", "Follow me home headlamps": "Yes  ", "Fog Lamps": "Front  ", "Tail Lights": "LED  ", "Cabin Lamps": "Front and Rear  ", "Glove Box Lamp": "Yes  ", "Lights on Vanity Mirrors": "Driver & Co-Driver  ", "Rear Reading Lamp": "Yes  ", "Cornering Headlights": "Active  "}, "Instrumentation": {"Instrument Cluster": "Digital  ", "Trip Meter": "Electronic 2 Trips  ", "Average Fuel Consumption": "Yes  ", "Average Speed": "Yes  ", "Distance to Empty": "Yes  ", "Clock": "Digital  ", "Low Fuel Level Warning": "Yes  ", "Door Ajar Warning": "Yes  ", "Adjustable Cluster Brightness": "Yes  ", "Gear Indicator": "Yes  ", "Shift Indicator": "Yes  ", "Heads Up Display (HUD)": "Yes  ", "Tachometer": "Digital  ", "Instantaneous Consumption": "Yes  "}, "Entertainment, Information & Communication": {"Integrated (in-dash) Music System": "Yes  ", "Head Unit Size": "2 Din  ", "Display": "Touch-screen Display  ", "GPS Navigation System": "Yes  ", "Speakers": "6+  ", "USB Compatibility": "Yes  ", "Aux Compatibility": "Yes  ", "Bluetooth Compatibility": "Phone & Audio Streaming  ", "MP3 Playback": "Yes  ", "CD Player": "Yes  ", "DVD Playback": "Yes  ", "AM/FM Radio": "Yes  ", "iPod Compatibility": "Yes  ", "Internal Hard-drive": "Yes  ", "Steering mounted controls": "Yes  ", "Voice Command": "Yes  "}, "Manufacturer Warranty": {"Warranty (Years)": "3  ", "Warranty (Kilometres)": "Unlimited  "}}}, "GranLusso ": {"key Specifications": {"Price": "Rs. 1.47 Crores", "Mileage": " 16.9 kmpl", "Engine": " 2987 cc", "Transmission": " Automatic", "FuelType": " Diesel"}, "spec": {"Engine & Transmission": {"Engine": "2987cc, 6 Cylinders In V Shape, 4 Valves/Cylinder, DOHC ", "Engine Type": "Turbocharged Diesel Engine ", "Fuel Type ": "Diesel ", "Max Power (bhp@rpm)": "275 bhp @ 4000 rpm ", "Max Torque (Nm@rpm)": "600 Nm @ 2000 rpm ", "Mileage (ARAI)": "16.9 kmpl", "Drivetrain": "RWD ", "Transmission": "Automatic - 8 Gears, Conventional + Paddle Shift, Sport Mode ", "Turbocharger / Supercharger": "Turbocharged, Fixed Geometry ", "Others": "Engine Start-Stop Function "}, "Dimensions & Weight": {"Length": "4971 mm", "Width": "1945 mm", "Height": "1461 mm", "Wheelbase": "2998 mm", "Kerb Weight": "1835 kg"}, "Capacity": {"Doors": "4 Doors", "Seating Capacity": "5 Person", "No of Seating Rows": "2 Rows", "Bootspace": "500 litres", "Fuel Tank Capacity": "70 litres"}, "Suspensions, Brakes & Steering ": {"Suspension Front": "McPherson Strut Independent suspension ", "Suspension Rear": "Independent suspension ", "Front Brake Type": "Disc ", "Rear Brake Type": "Disc ", "Minimum Turning Radius": "5.85 metres", "Steering Type": "Power assisted (Electric) ", "Wheels": "Alloy Wheels ", "Spare Wheel": "Alloy ", "Front Tyres": "\r\n\t\t\t\t\t\t\t\t\t\t\t\t\t\t\t\t\t50 / 235 R18 \r\n\t\t\t\t\t\t\t\t\t\t\t\t\t\t\t\t", "Rear Tyres": "50 / 235 R18 "}}, "fea": {"Safety": {"Airbags": "7 Airbags  ", "Dual-Stage Airbags": "Yes  ", "Middle rear three-point seatbelt": "Yes  ", "Middle Rear Head Rest": "Yes  ", "Tyre Pressure Monitoring System (TPMS)": "Yes  ", "Child Seat Anchor Points": "Yes  ", "Seat Belt Warning": "Yes  "}, "Braking & Traction": {"Anti-Lock Braking System (ABS)": "Yes  ", "Electronic Brake-force Distribution (EBD)": "Yes  ", "Brake Assist (BA)": "Yes  ", "Electronic Stability Program (ESP)": "Yes  ", "Hill Hold Control": "Yes  ", "Traction Control System (TC/TCS)": "Yes  ", "Ride Height Adjustment": "Yes  ", "Hill Descent Control": "Yes  ", "Limited Slip Differential (LSD)": "Yes  ", "Differential Lock": "Electronic  "}, "Locks & Security": {"Engine immobilizer": "Yes  ", "Central Locking": "Keyless  ", "Speed Sensing Door Lock": "Yes  ", "Child Safety Lock": "Yes  "}, "Comfort & Convenience": {"Air Conditioner": "Automatic - Three Zone  ", "Rear AC": "Blower  ", "12V Power Outlets": "2  ", "Steering Adjustment": "Electric Tilt & Telescopic  ", "Headlight off and lgnition Key Off Reminder": "Yes  ", "Cruise Control": "Yes  ", "Parking Sensors": "Front & Rear  ", "Parking Assist": "Reverse Camera with Guidance  ", "Anti-glare Mirrors": "Electronic - All  ", "Cabin-Boot Access": "Yes  ", "Vanity Mirrors on Sun Visors": "Driver & Co-Driver  ", "Heater": "Yes  "}, "Seats & Upholstery": {"Seat Upholstery": "Leather  ", "Leather-wrapped Steering Wheel": "Yes  ", "Leather-wrapped Gear Knob": "Yes  ", "Driver Seat Adjustment": "Electrically Adjustable with Memory Function  ", "Front Passenger Seat Adjustment": "Electrically Adjustable with Memory Function  ", "Lumbar Support": "Driver & Co-Driver  ", "Adjustable Lumbar Support": "Electric - 4 way  ", "Driver Armrest": "Yes  ", "Rear Passenger Seats": "Bench  ", "Rear Passenger Adjustable seats": "Electrically Adjustable with Memory Function  ", "3rd Row Seats": "Bench  ", "Ventilated Seats": "All  ", "Ventilated Seat Type": "Heated and cooled  ", "Interiors": "Single Tone  ", "Rear Armrest": "With Cup Holder  ", "Split Rear Seat": "60:40 split  ", "Front Seat Pockets": "Yes  ", "Adjustable Head-rests": "Front & Rear  ", "Electrically Adjustable Headrests": "Front & Rear  ", "Head-rests": "Front & Rear  "}, "Storage": {"Cup Holders": "Front & Rear  ", "Driver Armrest Storage": "Yes  ", "Cooled Glove Box ": "Yes  ", "Sunglass Holder": "Yes  "}, "Doors, Windows, Mirrors & Wipers": {"Power Windows": "Front & Rear  ", "One Touch -Down": "All  ", "One Touch - Up": "All  ", "Adjustable ORVM": "Electrically Adjustable & Retractable  ", "Turn Indicators on ORVM": "Yes  ", "Rear Defogger": "Yes  ", "Exterior Door Handles": "Body Coloured  ", "Rain-sensing Wipers": "Yes  ", "Interior Door Handles": "Chrome  ", "Door Pockets": "Front & Rear  ", "Door Blinds": "Rear - electric  ", "Boot-lid Opener": "Internal with Remote  ", "Rear Window Blind": "Electric  ", "Outside Rear View Mirrors (ORVMs)": "Body Coloured  "}, "Exterior": {"Sunroof / Moonroof": "Electrically Adjustable  ", "Roof Mounted Antenna": "Yes  ", "Body-Coloured  Bumpers ": "Yes  ", "Chrome Finish Exhaust pipe": "Yes  "}, "Lighting": {"Headlights": "LED  ", "Automatic Head Lamps": "Yes  ", "Follow me home headlamps": "Yes  ", "Fog Lamps": "Front  ", "Tail Lights": "LED  ", "Cabin Lamps": "Front and Rear  ", "Glove Box Lamp": "Yes  ", "Lights on Vanity Mirrors": "Driver & Co-Driver  ", "Rear Reading Lamp": "Yes  ", "Cornering Headlights": "Active  "}, "Instrumentation": {"Instrument Cluster": "Digital  ", "Trip Meter": "Electronic 2 Trips  ", "Average Fuel Consumption": "Yes  ", "Average Speed": "Yes  ", "Distance to Empty": "Yes  ", "Clock": "Digital  ", "Low Fuel Level Warning": "Yes  ", "Door Ajar Warning": "Yes  ", "Adjustable Cluster Brightness": "Yes  ", "Gear Indicator": "Yes  ", "Shift Indicator": "Yes  ", "Heads Up Display (HUD)": "Yes  ", "Tachometer": "Digital  ", "Instantaneous Consumption": "Yes  "}, "Entertainment, Information & Communication": {"Integrated (in-dash) Music System": "Yes  ", "Head Unit Size": "2 Din  ", "Display": "Touch-screen Display  ", "GPS Navigation System": "Yes  ", "Speakers": "6+  ", "USB Compatibility": "Yes  ", "Aux Compatibility": "Yes  ", "Bluetooth Compatibility": "Phone & Audio Streaming  ", "MP3 Playback": "Yes  ", "CD Player": "Yes  ", "DVD Playback": "Yes  ", "AM/FM Radio": "Yes  ", "iPod Compatibility": "Yes  ", "Internal Hard-drive": "Yes  ", "Steering mounted controls": "Yes  ", "Voice Command": "Yes  "}, "Manufacturer Warranty": {"Warranty (Years)": "3  ", "Warranty (Kilometres)": "Unlimited  "}}}}}, "levante": {"gen": {"Price": "Rs. 1.5 Crores onwards", "Engine": " 2979 to 2987 cc", "Transmission": " Automatic", "FuelType": " Diesel", "Seating Capacity": " 5"}, "detail": {"Diesel ": {"key Specifications": {"Price": "Rs. 1.5 Crores", "Engine": " 2987 cc", "Transmission": " Automatic", "FuelType": " Diesel", "Seating Capacity": " 5"}, "spec": {"Engine & Transmission": {"Engine": "2987cc, 6 Cylinders In V Shape, 4 Valves/Cylinder, DOHC ", "Engine Type": "Turbocharged Diesel Engine ", "Fuel Type ": "Diesel ", "Max Power (bhp@rpm)": "271 bhp @ 4000 rpm ", "Max Torque (Nm@rpm)": "600 Nm @ 2000 rpm ", "Drivetrain": "AWD ", "Transmission": "Automatic - 8 Gears, Conventional + Paddle Shift, Sport Mode ", "Turbocharger / Supercharger": "Twin Turbo, Variable Geometry ", "Others": "Engine Start-Stop Function "}, "Dimensions & Weight": {"Length": "5003 mm", "Width": "1968 mm", "Height": "1679 mm", "Wheelbase": "3004 mm"}, "Capacity": {"Doors": "5 Doors", "Seating Capacity": "5 Person", "No of Seating Rows": "2 Rows", "Bootspace": "580 litres", "Fuel Tank Capacity": "80 litres"}, "Suspensions, Brakes & Steering ": {"Suspension Front": "McPherson Strut Independent suspension ", "Suspension Rear": "Independent suspension ", "Front Brake Type": "Disc ", "Rear Brake Type": "Disc ", "Minimum Turning Radius": "5.85 metres", "Steering Type": "Power assisted (Electric) ", "Wheels": "Alloy Wheels ", "Spare Wheel": "Alloy ", "Front Tyres": "\r\n\t\t\t\t\t\t\t\t\t\t\t\t\t\t\t\t\t60 / 255 R18 \r\n\t\t\t\t\t\t\t\t\t\t\t\t\t\t\t\t", "Rear Tyres": "60 / 255 R18 "}}, "fea": {"Safety": {"Airbags": "6 Airbags  ", "Dual-Stage Airbags": "Yes  ", "Middle rear three-point seatbelt": "Yes  ", "Middle Rear Head Rest": "Yes  ", "Tyre Pressure Monitoring System (TPMS)": "Yes  ", "Child Seat Anchor Points": "Yes  ", "Seat Belt Warning": "Yes  "}, "Braking & Traction": {"Anti-Lock Braking System (ABS)": "Yes  ", "Electronic Brake-force Distribution (EBD)": "Yes  ", "Brake Assist (BA)": "Yes  ", "Electronic Stability Program (ESP)": "Yes  ", "Four-Wheel-Drive": "Torque-On-Demand  ", "Hill Hold Control": "Yes  ", "Traction Control System (TC/TCS)": "Yes  ", "Ride Height Adjustment": "Yes  ", "Hill Descent Control": "Yes  ", "Differential Lock": "Electronic  "}, "Locks & Security": {"Engine immobilizer": "Yes  ", "Central Locking": "Keyless  ", "Speed Sensing Door Lock": "Yes  ", "Child Safety Lock": "Yes  "}, "Comfort & Convenience": {"Air Conditioner": "Automatic - Three Zone  ", "Rear AC": "Blower  ", "12V Power Outlets": "2  ", "Steering Adjustment": "Electric Tilt & Telescopic  ", "Headlight off and lgnition Key Off Reminder": "Yes  ", "Cruise Control": "Yes  ", "Parking Sensors": "Front & Rear  ", "Parking Assist": "Reverse Camera with Guidance  ", "Anti-glare Mirrors": "Electronic - All  ", "Cabin-Boot Access": "Yes  ", "Vanity Mirrors on Sun Visors": "Driver & Co-Driver  ", "Heater": "Yes  "}, "Seats & Upholstery": {"Seat Upholstery": "Leather  ", "Leather-wrapped Steering Wheel": "Yes  ", "Leather-wrapped Gear Knob": "Yes  ", "Driver Seat Adjustment": "Electrically Adjustable with Memory Function  ", "Front Passenger Seat Adjustment": "Electrically Adjustable with Memory Function  ", "Lumbar Support": "Driver & Co-Driver  ", "Adjustable Lumbar Support": "Electric - 4 way  ", "Driver Armrest": "Yes  ", "Rear Passenger Seats": "Bench  ", "Rear Passenger Adjustable seats": "Electrically Adjustable with Memory Function  ", "Ventilated Seats": "All  ", "Ventilated Seat Type": "Heated  ", "Interiors": "Single Tone  ", "Rear Armrest": "With Cup Holder  ", "Split Rear Seat": "50:50 split  ", "Front Seat Pockets": "Yes  ", "Adjustable Head-rests": "Front & Rear  ", "Electrically Adjustable Headrests": "Front & Rear  ", "Head-rests": "Front & Rear  "}, "Storage": {"Cup Holders": "Front & Rear  ", "Driver Armrest Storage": "Yes  ", "Cooled Glove Box ": "Yes  ", "Sunglass Holder": "Yes  "}, "Doors, Windows, Mirrors & Wipers": {"Power Windows": "Front & Rear  ", "One Touch -Down": "All  ", "One Touch - Up": "All  ", "Adjustable ORVM": "Electrically Adjustable & Retractable  ", "Turn Indicators on ORVM": "Yes  ", "Rear Defogger": "Yes  ", "Exterior Door Handles": "Chrome  ", "Rain-sensing Wipers": "Yes  ", "Interior Door Handles": "Chrome  ", "Door Pockets": "Front & Rear  ", "Door Blinds": "Front and Rear Electric  ", "Boot-lid Opener": "Internal with Remote  ", "Rear Window Blind": "Electric  ", "Outside Rear View Mirrors (ORVMs)": "Body Coloured  "}, "Exterior": {"Sunroof / Moonroof": "Electrically Adjustable  ", "Roof Mounted Antenna": "Yes  ", "Body-Coloured  Bumpers ": "Yes  ", "Chrome Finish Exhaust pipe": "Yes  "}, "Lighting": {"Headlights": "LED  ", "Automatic Head Lamps": "Yes  ", "Follow me home headlamps": "Yes  ", "Fog Lamps": "Front  ", "Tail Lights": "LED  ", "Cabin Lamps": "Front  ", "Glove Box Lamp": "Yes  ", "Lights on Vanity Mirrors": "Driver & Co-Driver  ", "Rear Reading Lamp": "Yes  ", "Cornering Headlights": "Active  "}, "Instrumentation": {"Instrument Cluster": "Digital  ", "Trip Meter": "2 Trips  ", "Average Fuel Consumption": "Yes  ", "Average Speed": "Yes  ", "Distance to Empty": "Yes  ", "Clock": "Digital  ", "Low Fuel Level Warning": "Yes  ", "Door Ajar Warning": "Yes  ", "Adjustable Cluster Brightness": "Yes  ", "Gear Indicator": "Yes  ", "Shift Indicator": "Yes  ", "Heads Up Display (HUD)": "Yes  ", "Tachometer": "Digital  ", "Instantaneous Consumption": "Yes  "}, "Entertainment, Information & Communication": {"Integrated (in-dash) Music System": "Yes  ", "Head Unit Size": "2 Din  ", "Display": "Touch-screen Display  ", "GPS Navigation System": "Yes  ", "Speakers": "6+  ", "USB Compatibility": "Yes  ", "Aux Compatibility": "Yes  ", "Bluetooth Compatibility": "Phone & Audio Streaming  ", "MP3 Playback": "Yes  ", "CD Player": "Yes  ", "DVD Playback": "Yes  ", "AM/FM Radio": "Yes  ", "iPod Compatibility": "Yes  ", "Steering mounted controls": "Yes  ", "Voice Command": "Yes  "}, "Manufacturer Warranty": {"Warranty (Years)": "3  ", "Warranty (Kilometres)": "Unlimited  "}}}, "GranSport ": {"key Specifications": {"Price": "Rs. 1.53 Crores", "Engine": " 2979 cc", "Transmission": " Automatic", "FuelType": " Diesel", "Seating Capacity": " 5"}, "spec": {"Engine & Transmission": {"Engine": "2979cc, 6 Cylinders In V Shape, 4 Valves/Cylinder, DOHC ", "Engine Type": "Turbocharged Diesel Engine ", "Fuel Type ": "Diesel ", "Max Power (bhp@rpm)": "345 bhp @ 5750 rpm ", "Max Torque (Nm@rpm)": "500 Nm @ 4500 rpm ", "Drivetrain": "AWD ", "Transmission": "Automatic - 8 Gears, Conventional + Paddle Shift, Sport Mode ", "Turbocharger / Supercharger": "Twin Turbo, Variable Geometry ", "Others": "Engine Start-Stop Function "}, "Dimensions & Weight": {"Length": "5003 mm", "Width": "1968 mm", "Height": "1679 mm", "Wheelbase": "3004 mm"}, "Capacity": {"Doors": "5 Doors", "Seating Capacity": "5 Person", "No of Seating Rows": "2 Rows", "Bootspace": "580 litres", "Fuel Tank Capacity": "80 litres"}, "Suspensions, Brakes & Steering ": {"Suspension Front": "McPherson Strut Independent suspension ", "Suspension Rear": "Independent suspension ", "Front Brake Type": "Disc ", "Rear Brake Type": "Disc ", "Minimum Turning Radius": "5.85 metres", "Steering Type": "Power assisted (Electric) ", "Wheels": "Alloy Wheels ", "Spare Wheel": "Alloy ", "Front Tyres": "\r\n\t\t\t\t\t\t\t\t\t\t\t\t\t\t\t\t\t60 / 255 R19 \r\n\t\t\t\t\t\t\t\t\t\t\t\t\t\t\t\t", "Rear Tyres": "60 / 255 R19 "}}, "fea": {"Safety": {"Airbags": "6 Airbags  ", "Dual-Stage Airbags": "Yes  ", "Middle rear three-point seatbelt": "Yes  ", "Middle Rear Head Rest": "Yes  ", "Tyre Pressure Monitoring System (TPMS)": "Yes  ", "Child Seat Anchor Points": "Yes  ", "Seat Belt Warning": "Yes  "}, "Braking & Traction": {"Anti-Lock Braking System (ABS)": "Yes  ", "Electronic Brake-force Distribution (EBD)": "Yes  ", "Brake Assist (BA)": "Yes  ", "Electronic Stability Program (ESP)": "Yes  ", "Four-Wheel-Drive": "Torque-On-Demand  ", "Hill Hold Control": "Yes  ", "Traction Control System (TC/TCS)": "Yes  ", "Ride Height Adjustment": "Yes  ", "Hill Descent Control": "Yes  ", "Differential Lock": "Electronic  "}, "Locks & Security": {"Engine immobilizer": "Yes  ", "Central Locking": "Keyless  ", "Speed Sensing Door Lock": "Yes  ", "Child Safety Lock": "Yes  "}, "Comfort & Convenience": {"Air Conditioner": "Automatic - Three Zone  ", "Rear AC": "Blower  ", "12V Power Outlets": "2  ", "Steering Adjustment": "Electric Tilt & Telescopic  ", "Headlight off and lgnition Key Off Reminder": "Yes  ", "Cruise Control": "Yes  ", "Parking Sensors": "Front & Rear  ", "Parking Assist": "Reverse Camera with Guidance  ", "Anti-glare Mirrors": "Electronic - All  ", "Cabin-Boot Access": "Yes  ", "Vanity Mirrors on Sun Visors": "Driver & Co-Driver  ", "Heater": "Yes  "}, "Seats & Upholstery": {"Seat Upholstery": "Leather  ", "Leather-wrapped Steering Wheel": "Yes  ", "Leather-wrapped Gear Knob": "Yes  ", "Driver Seat Adjustment": "Electrically Adjustable with Memory Function  ", "Front Passenger Seat Adjustment": "Electrically Adjustable with Memory Function  ", "Lumbar Support": "Driver & Co-Driver  ", "Adjustable Lumbar Support": "Electric - 4 way  ", "Driver Armrest": "Yes  ", "Rear Passenger Seats": "Bench  ", "Rear Passenger Adjustable seats": "Electrically Adjustable with Memory Function  ", "Ventilated Seats": "All  ", "Ventilated Seat Type": "Heated  ", "Interiors": "Single Tone  ", "Rear Armrest": "With Cup Holder  ", "Split Rear Seat": "50:50 split  ", "Front Seat Pockets": "Yes  ", "Adjustable Head-rests": "Front & Rear  ", "Electrically Adjustable Headrests": "Front & Rear  ", "Head-rests": "Front & Rear  "}, "Storage": {"Cup Holders": "Front & Rear  ", "Driver Armrest Storage": "Yes  ", "Cooled Glove Box ": "Yes  ", "Sunglass Holder": "Yes  "}, "Doors, Windows, Mirrors & Wipers": {"Power Windows": "Front & Rear  ", "One Touch -Down": "All  ", "One Touch - Up": "All  ", "Adjustable ORVM": "Electrically Adjustable & Retractable  ", "Turn Indicators on ORVM": "Yes  ", "Rear Defogger": "Yes  ", "Exterior Door Handles": "Chrome  ", "Rain-sensing Wipers": "Yes  ", "Interior Door Handles": "Chrome  ", "Door Pockets": "Front & Rear  ", "Door Blinds": "Front and Rear Electric  ", "Boot-lid Opener": "Internal with Remote  ", "Rear Window Blind": "Electric  ", "Outside Rear View Mirrors (ORVMs)": "Body Coloured  "}, "Exterior": {"Sunroof / Moonroof": "Electrically Adjustable  ", "Roof Mounted Antenna": "Yes  ", "Body-Coloured  Bumpers ": "Yes  ", "Chrome Finish Exhaust pipe": "Yes  "}, "Lighting": {"Headlights": "LED  ", "Automatic Head Lamps": "Yes  ", "Follow me home headlamps": "Yes  ", "Fog Lamps": "Front  ", "Tail Lights": "LED  ", "Cabin Lamps": "Front  ", "Glove Box Lamp": "Yes  ", "Lights on Vanity Mirrors": "Driver & Co-Driver  ", "Rear Reading Lamp": "Yes  ", "Cornering Headlights": "Active  "}, "Instrumentation": {"Instrument Cluster": "Digital  ", "Trip Meter": "2 Trips  ", "Average Fuel Consumption": "Yes  ", "Average Speed": "Yes  ", "Distance to Empty": "Yes  ", "Clock": "Digital  ", "Low Fuel Level Warning": "Yes  ", "Door Ajar Warning": "Yes  ", "Adjustable Cluster Brightness": "Yes  ", "Gear Indicator": "Yes  ", "Shift Indicator": "Yes  ", "Heads Up Display (HUD)": "Yes  ", "Tachometer": "Digital  ", "Instantaneous Consumption": "Yes  "}, "Entertainment, Information & Communication": {"Integrated (in-dash) Music System": "Yes  ", "Head Unit Size": "2 Din  ", "Display": "Touch-screen Display  ", "GPS Navigation System": "Yes  ", "Speakers": "6+  ", "USB Compatibility": "Yes  ", "Aux Compatibility": "Yes  ", "Bluetooth Compatibility": "Phone & Audio Streaming  ", "MP3 Playback": "Yes  ", "CD Player": "Yes  ", "DVD Playback": "Yes  ", "AM/FM Radio": "Yes  ", "iPod Compatibility": "Yes  ", "Steering mounted controls": "Yes  ", "Voice Command": "Yes  "}, "Manufacturer Warranty": {"Warranty (Years)": "3  ", "Warranty (Kilometres)": "Unlimited  "}}}, "GranLusso ": {"key Specifications": {"Price": "Rs. 1.58 Crores", "Engine": " 2979 cc", "Transmission": " Automatic", "FuelType": " Diesel", "Seating Capacity": " 5"}, "spec": {"Engine & Transmission": {"Engine": "2979cc, 6 Cylinders In V Shape, 4 Valves/Cylinder, DOHC ", "Engine Type": "Turbocharged Diesel Engine ", "Fuel Type ": "Diesel ", "Max Power (bhp@rpm)": "424 bhp @ 5750 rpm ", "Max Torque (Nm@rpm)": "580 Nm @ 4500 rpm ", "Drivetrain": "AWD ", "Transmission": "Automatic - 8 Gears, Conventional + Paddle Shift, Sport Mode ", "Turbocharger / Supercharger": "Twin Turbo, Variable Geometry ", "Others": "Engine Start-Stop Function "}, "Dimensions & Weight": {"Length": "5003 mm", "Width": "1968 mm", "Height": "1679 mm", "Wheelbase": "3004 mm"}, "Capacity": {"Doors": "5 Doors", "Seating Capacity": "5 Person", "No of Seating Rows": "2 Rows", "Bootspace": "580 litres", "Fuel Tank Capacity": "80 litres"}, "Suspensions, Brakes & Steering ": {"Suspension Front": "McPherson Strut Independent suspension ", "Suspension Rear": "Independent suspension ", "Front Brake Type": "Disc ", "Rear Brake Type": "Disc ", "Minimum Turning Radius": "5.85 metres", "Steering Type": "Power assisted (Electric) ", "Wheels": "Alloy Wheels ", "Spare Wheel": "Alloy ", "Front Tyres": "\r\n\t\t\t\t\t\t\t\t\t\t\t\t\t\t\t\t\t60 / 255 R20 \r\n\t\t\t\t\t\t\t\t\t\t\t\t\t\t\t\t", "Rear Tyres": "60 / 255 R20 "}}, "fea": {"Safety": {"Airbags": "6 Airbags  ", "Dual-Stage Airbags": "Yes  ", "Middle rear three-point seatbelt": "Yes  ", "Middle Rear Head Rest": "Yes  ", "Tyre Pressure Monitoring System (TPMS)": "Yes  ", "Child Seat Anchor Points": "Yes  ", "Seat Belt Warning": "Yes  "}, "Braking & Traction": {"Anti-Lock Braking System (ABS)": "Yes  ", "Electronic Brake-force Distribution (EBD)": "Yes  ", "Brake Assist (BA)": "Yes  ", "Electronic Stability Program (ESP)": "Yes  ", "Four-Wheel-Drive": "Torque-On-Demand  ", "Hill Hold Control": "Yes  ", "Traction Control System (TC/TCS)": "Yes  ", "Ride Height Adjustment": "Yes  ", "Hill Descent Control": "Yes  ", "Differential Lock": "Electronic  "}, "Locks & Security": {"Engine immobilizer": "Yes  ", "Central Locking": "Keyless  ", "Speed Sensing Door Lock": "Yes  ", "Child Safety Lock": "Yes  "}, "Comfort & Convenience": {"Air Conditioner": "Automatic - Three Zone  ", "Rear AC": "Blower  ", "12V Power Outlets": "2  ", "Steering Adjustment": "Electric Tilt & Telescopic  ", "Headlight off and lgnition Key Off Reminder": "Yes  ", "Cruise Control": "Yes  ", "Parking Sensors": "Front & Rear  ", "Parking Assist": "Reverse Camera with Guidance  ", "Anti-glare Mirrors": "Electronic - All  ", "Cabin-Boot Access": "Yes  ", "Vanity Mirrors on Sun Visors": "Driver & Co-Driver  ", "Heater": "Yes  "}, "Seats & Upholstery": {"Seat Upholstery": "Leather  ", "Leather-wrapped Steering Wheel": "Yes  ", "Leather-wrapped Gear Knob": "Yes  ", "Driver Seat Adjustment": "Electrically Adjustable with Memory Function  ", "Front Passenger Seat Adjustment": "Electrically Adjustable with Memory Function  ", "Lumbar Support": "Driver & Co-Driver  ", "Adjustable Lumbar Support": "Electric - 4 way  ", "Driver Armrest": "Yes  ", "Rear Passenger Seats": "Bench  ", "Rear Passenger Adjustable seats": "Electrically Adjustable with Memory Function  ", "Ventilated Seats": "All  ", "Ventilated Seat Type": "Heated  ", "Interiors": "Single Tone  ", "Rear Armrest": "With Cup Holder  ", "Split Rear Seat": "50:50 split  ", "Front Seat Pockets": "Yes  ", "Adjustable Head-rests": "Front & Rear  ", "Electrically Adjustable Headrests": "Front & Rear  ", "Head-rests": "Front & Rear  "}, "Storage": {"Cup Holders": "Front & Rear  ", "Driver Armrest Storage": "Yes  ", "Cooled Glove Box ": "Yes  ", "Sunglass Holder": "Yes  "}, "Doors, Windows, Mirrors & Wipers": {"Power Windows": "Front & Rear  ", "One Touch -Down": "All  ", "One Touch - Up": "All  ", "Adjustable ORVM": "Electrically Adjustable & Retractable  ", "Turn Indicators on ORVM": "Yes  ", "Rear Defogger": "Yes  ", "Exterior Door Handles": "Chrome  ", "Rain-sensing Wipers": "Yes  ", "Interior Door Handles": "Chrome  ", "Door Pockets": "Front & Rear  ", "Door Blinds": "Front and Rear Electric  ", "Boot-lid Opener": "Internal with Remote  ", "Rear Window Blind": "Electric  ", "Outside Rear View Mirrors (ORVMs)": "Body Coloured  "}, "Exterior": {"Sunroof / Moonroof": "Electrically Adjustable  ", "Roof Mounted Antenna": "Yes  ", "Body-Coloured  Bumpers ": "Yes  ", "Chrome Finish Exhaust pipe": "Yes  "}, "Lighting": {"Headlights": "LED  ", "Automatic Head Lamps": "Yes  ", "Follow me home headlamps": "Yes  ", "Fog Lamps": "Front  ", "Tail Lights": "LED  ", "Cabin Lamps": "Front  ", "Glove Box Lamp": "Yes  ", "Lights on Vanity Mirrors": "Driver & Co-Driver  ", "Rear Reading Lamp": "Yes  ", "Cornering Headlights": "Active  "}, "Instrumentation": {"Instrument Cluster": "Digital  ", "Trip Meter": "2 Trips  ", "Average Fuel Consumption": "Yes  ", "Average Speed": "Yes  ", "Distance to Empty": "Yes  ", "Clock": "Digital  ", "Low Fuel Level Warning": "Yes  ", "Door Ajar Warning": "Yes  ", "Adjustable Cluster Brightness": "Yes  ", "Gear Indicator": "Yes  ", "Shift Indicator": "Yes  ", "Heads Up Display (HUD)": "Yes  ", "Tachometer": "Digital  ", "Instantaneous Consumption": "Yes  "}, "Entertainment, Information & Communication": {"Integrated (in-dash) Music System": "Yes  ", "Head Unit Size": "2 Din  ", "Display": "Touch-screen Display  ", "GPS Navigation System": "Yes  ", "Speakers": "6+  ", "USB Compatibility": "Yes  ", "Aux Compatibility": "Yes  ", "Bluetooth Compatibility": "Phone & Audio Streaming  ", "MP3 Playback": "Yes  ", "CD Player": "Yes  ", "DVD Playback": "Yes  ", "AM/FM Radio": "Yes  ", "iPod Compatibility": "Yes  ", "Steering mounted controls": "Yes  ", "Voice Command": "Yes  "}, "Manufacturer Warranty": {"Warranty (Years)": "3  ", "Warranty (Kilometres)": "Unlimited  "}}}}}, "granturismo": {"gen": {"Price": "Rs. 2.25 Crores onwards", "Engine": " 4691 cc", "Transmission": " Automatic", "FuelType": " Petrol", "Seating Capacity": " 4"}, "detail": {"4.7 V8 MC ": {"key Specifications": {"Price": "Rs. 2.25 Crores", "Engine": " 4691 cc", "Transmission": " Automatic", "FuelType": " Petrol", "Seating Capacity": " 4"}, "spec": {"Engine & Transmission": {"Engine": "4691cc, 8 Cylinders In V Shape, 4 Valves/Cylinder, DOHC ", "Engine Type": "M139S ", "Fuel Type ": "Petrol ", "Max Power (bhp@rpm)": "453 bhp @ 7000 rpm ", "Max Torque (Nm@rpm)": "520 Nm @ 4750 rpm ", "Drivetrain": "RWD ", "Transmission": "Automatic - 6 Gears, Dual Clutch, Conventional + Paddle Shift, Sport Mode ", "Turbocharger / Supercharger": "Yes, Fixed Geometry ", "Others": "Engine Start-Stop Function "}, "Dimensions & Weight": {"Length": "4920 mm", "Width": "2056 mm", "Height": "1380 mm", "Wheelbase": "2942 mm", "Kerb Weight": "1773 kg"}, "Capacity": {"Doors": "2 Doors", "Seating Capacity": "4 Person", "No of Seating Rows": "2 Rows", "Bootspace": "260 litres", "Fuel Tank Capacity": "86 litres"}, "Suspensions, Brakes & Steering ": {"Suspension Front": "double wishbone suspension with forged aluminium arms & hubs ", "Suspension Rear": "double wishbone suspension with forged aluminium arms & hubs ", "Front Brake Type": "Disc ", "Rear Brake Type": "Disc ", "Minimum Turning Radius": "5.35 metres", "Steering Type": "Power assisted (Electric) ", "Wheels": "Alloy Wheels ", "Spare Wheel": "Alloy ", "Front Tyres": "\r\n\t\t\t\t\t\t\t\t\t\t\t\t\t\t\t\t\t245 / 35 R20 \r\n\t\t\t\t\t\t\t\t\t\t\t\t\t\t\t\t", "Rear Tyres": "285 / 35 R20 "}}, "fea": {"Safety": {"Airbags": "6 Airbags  ", "Dual-Stage Airbags": "Yes  ", "Middle rear three-point seatbelt": "Yes  ", "Middle Rear Head Rest": "Yes  ", "Tyre Pressure Monitoring System (TPMS)": "Yes  ", "Child Seat Anchor Points": "Yes  ", "Seat Belt Warning": "Yes  "}, "Braking & Traction": {"Anti-Lock Braking System (ABS)": "Yes  ", "Electronic Brake-force Distribution (EBD)": "Yes  ", "Brake Assist (BA)": "Yes  ", "Electronic Stability Program (ESP)": "Yes  ", "Hill Hold Control": "Yes  ", "Traction Control System (TC/TCS)": "Yes  ", "Ride Height Adjustment": "Yes  ", "Hill Descent Control": "Yes  ", "Limited Slip Differential (LSD)": "Yes  ", "Differential Lock": "Electronic  "}, "Locks & Security": {"Engine immobilizer": "Yes  ", "Central Locking": "Remote  ", "Speed Sensing Door Lock": "Yes  ", "Child Safety Lock": "Yes  "}, "Comfort & Convenience": {"Air Conditioner": "Automatic Climate Control  ", "Rear AC": "Vents Only  ", "12V Power Outlets": "Yes  ", "Steering Adjustment": "Tilt & Telescopic  ", "Headlight off and lgnition Key Off Reminder": "Yes  ", "Cruise Control": "Yes  ", "Parking Sensors": "Front & Rear  ", "Parking Assist": "Reverse Camera with Guidance  ", "Anti-glare Mirrors": "Electronic - All  ", "Cabin-Boot Access": "Yes  ", "Vanity Mirrors on Sun Visors": "Driver & Co-Driver  ", "Heater": "Yes  "}, "Seats & Upholstery": {"Seat Upholstery": "Leather  ", "Leather-wrapped Steering Wheel": "Yes  ", "Leather-wrapped Gear Knob": "Yes  ", "Driver Seat Adjustment": "Electrically Adjustable with Memory Function  ", "Front Passenger Seat Adjustment": "Electrically Adjustable with Memory Function  ", "Lumbar Support": "Driver Only  ", "Adjustable Lumbar Support": "Electric - 2 way  ", "Driver Armrest": "Yes  ", "Rear Passenger Seats": "Bench  ", "Rear Passenger Adjustable seats": "Electrically Adjustable with Memory Function  ", "Ventilated Seats": "Front only  ", "Ventilated Seat Type": "Heated  ", "Rear Armrest": "Yes  ", "Folding Rear Seat": "Full  ", "Split Rear Seat": "60:40 split  ", "Front Seat Pockets": "Yes  ", "Adjustable Head-rests": "Front & Rear  ", "Electrically Adjustable Headrests": "Front & Rear  ", "Head-rests": "Front & Rear  "}, "Storage": {"Cup Holders": "Front & Rear  ", "Driver Armrest Storage": "Yes  ", "Cooled Glove Box ": "Yes  ", "Sunglass Holder": "Yes  "}, "Doors, Windows, Mirrors & Wipers": {"Power Windows": "Front Only  ", "One Touch -Down": "All  ", "One Touch - Up": "All  ", "Adjustable ORVM": "Electrically Adjustable & Retractable  ", "Turn Indicators on ORVM": "Yes  ", "Rear Defogger": "Yes  ", "Exterior Door Handles": "Body Coloured  ", "Rain-sensing Wipers": "Yes  ", "Interior Door Handles": "Chrome  ", "Door Blinds": "Rear - electric  ", "Boot-lid Opener": "Internal with Remote  ", "Rear Window Blind": "Electric  ", "Outside Rear View Mirrors (ORVMs)": "Body Coloured  "}, "Exterior": {"Sunroof / Moonroof": "Panoramic Sunroof  ", "Roof Mounted Antenna": "Yes  ", "Body-Coloured  Bumpers ": "Yes  ", "Chrome Finish Exhaust pipe": "Yes  "}, "Lighting": {"Headlights": "LED  ", "Automatic Head Lamps": "Yes  ", "Follow me home headlamps": "Yes  ", "Fog Lamps": "Front & Rear  ", "Tail Lights": "LED  ", "Cabin Lamps": "Front  ", "Headlight Height Adjuster": "Yes  ", "Glove Box Lamp": "Yes  ", "Lights on Vanity Mirrors": "Driver & Co-Driver  ", "Rear Reading Lamp": "Yes  ", "Cornering Headlights": "Active  "}, "Instrumentation": {"Instrument Cluster": "Digital  ", "Trip Meter": "2 Trips  ", "Average Fuel Consumption": "Yes  ", "Average Speed": "Yes  ", "Distance to Empty": "Yes  ", "Clock": "Digital  ", "Low Fuel Level Warning": "Yes  ", "Door Ajar Warning": "Yes  ", "Adjustable Cluster Brightness": "Yes  ", "Gear Indicator": "Yes  ", "Shift Indicator": "Yes  ", "Heads Up Display (HUD)": "Yes  ", "Tachometer": "Digital  ", "Instantaneous Consumption": "Yes  "}, "Entertainment, Information & Communication": {"Integrated (in-dash) Music System": "Yes  ", "Head Unit Size": "2 Din  ", "Display": "Touch-screen Display  ", "GPS Navigation System": "Yes  ", "Speakers": "6+  ", "USB Compatibility": "Yes  ", "Aux Compatibility": "Yes  ", "Bluetooth Compatibility": "Phone & Audio Streaming  ", "MP3 Playback": "Yes  ", "CD Player": "Yes  ", "AM/FM Radio": "Yes  ", "iPod Compatibility": "Yes  ", "Steering mounted controls": "Yes  ", "Voice Command": "Yes  "}, "Manufacturer Warranty": {"Warranty (Years)": "3  ", "Warranty (Kilometres)": "Unlimited  "}}}, "4.7 V8 Sport ": {"key Specifications": {"Price": "Rs. 2.48 Crores", "Engine": " 4691 cc", "Transmission": " Automatic", "FuelType": " Petrol", "Seating Capacity": " 4"}, "spec": {"Engine & Transmission": {"Engine": "4691cc, 8 Cylinders In V Shape, 4 Valves/Cylinder, DOHC ", "Engine Type": "M139S ", "Fuel Type ": "Petrol ", "Max Power (bhp@rpm)": "453 bhp @ 7000 rpm ", "Max Torque (Nm@rpm)": "520 Nm @ 4750 rpm ", "Drivetrain": "RWD ", "Transmission": "Automatic - 6 Gears, Dual Clutch, Conventional + Paddle Shift, Sport Mode ", "Turbocharger / Supercharger": "Yes, Fixed Geometry ", "Others": "Engine Start-Stop Function "}, "Dimensions & Weight": {"Length": "4910 mm", "Width": "2056 mm", "Height": "1380 mm", "Wheelbase": "2942 mm", "Kerb Weight": "1780 kg"}, "Capacity": {"Doors": "2 Doors", "Seating Capacity": "4 Person", "No of Seating Rows": "2 Rows", "Bootspace": "260 litres", "Fuel Tank Capacity": "86 litres"}, "Suspensions, Brakes & Steering ": {"Suspension Front": "double wishbone suspension with forged aluminium arms & hubs ", "Suspension Rear": "double wishbone suspension with forged aluminium arms & hubs ", "Front Brake Type": "Disc ", "Rear Brake Type": "Disc ", "Minimum Turning Radius": "5.35 metres", "Steering Type": "Power assisted (Electric) ", "Wheels": "Alloy Wheels ", "Spare Wheel": "Alloy ", "Front Tyres": "\r\n\t\t\t\t\t\t\t\t\t\t\t\t\t\t\t\t\t245 / 35 R20 \r\n\t\t\t\t\t\t\t\t\t\t\t\t\t\t\t\t", "Rear Tyres": "285 / 35 R20 "}}, "fea": {"Safety": {"Airbags": "6 Airbags  ", "Dual-Stage Airbags": "Yes  ", "Middle rear three-point seatbelt": "Yes  ", "Middle Rear Head Rest": "Yes  ", "Tyre Pressure Monitoring System (TPMS)": "Yes  ", "Child Seat Anchor Points": "Yes  ", "Seat Belt Warning": "Yes  "}, "Braking & Traction": {"Anti-Lock Braking System (ABS)": "Yes  ", "Electronic Brake-force Distribution (EBD)": "Yes  ", "Brake Assist (BA)": "Yes  ", "Electronic Stability Program (ESP)": "Yes  ", "Hill Hold Control": "Yes  ", "Traction Control System (TC/TCS)": "Yes  ", "Ride Height Adjustment": "Yes  ", "Hill Descent Control": "Yes  ", "Limited Slip Differential (LSD)": "Yes  ", "Differential Lock": "Electronic  "}, "Locks & Security": {"Engine immobilizer": "Yes  ", "Central Locking": "Remote  ", "Speed Sensing Door Lock": "Yes  ", "Child Safety Lock": "Yes  "}, "Comfort & Convenience": {"Air Conditioner": "Automatic Climate Control  ", "Rear AC": "Vents Only  ", "12V Power Outlets": "Yes  ", "Steering Adjustment": "Tilt & Telescopic  ", "Headlight off and lgnition Key Off Reminder": "Yes  ", "Cruise Control": "Yes  ", "Parking Sensors": "Front & Rear  ", "Parking Assist": "Reverse Camera with Guidance  ", "Anti-glare Mirrors": "Electronic - All  ", "Cabin-Boot Access": "Yes  ", "Vanity Mirrors on Sun Visors": "Driver & Co-Driver  ", "Heater": "Yes  "}, "Seats & Upholstery": {"Seat Upholstery": "Leather  ", "Leather-wrapped Steering Wheel": "Yes  ", "Leather-wrapped Gear Knob": "Yes  ", "Driver Seat Adjustment": "Electrically Adjustable with Memory Function  ", "Front Passenger Seat Adjustment": "Electrically Adjustable with Memory Function  ", "Lumbar Support": "Driver Only  ", "Adjustable Lumbar Support": "Electric - 2 way  ", "Driver Armrest": "Yes  ", "Rear Passenger Seats": "Bench  ", "Rear Passenger Adjustable seats": "Electrically Adjustable with Memory Function  ", "Ventilated Seats": "Front only  ", "Ventilated Seat Type": "Heated  ", "Rear Armrest": "Yes  ", "Folding Rear Seat": "Full  ", "Split Rear Seat": "60:40 split  ", "Front Seat Pockets": "Yes  ", "Adjustable Head-rests": "Front & Rear  ", "Electrically Adjustable Headrests": "Front & Rear  ", "Head-rests": "Front & Rear  "}, "Storage": {"Cup Holders": "Front & Rear  ", "Driver Armrest Storage": "Yes  ", "Cooled Glove Box ": "Yes  ", "Sunglass Holder": "Yes  "}, "Doors, Windows, Mirrors & Wipers": {"Power Windows": "Front Only  ", "One Touch -Down": "All  ", "One Touch - Up": "All  ", "Adjustable ORVM": "Electrically Adjustable & Retractable  ", "Turn Indicators on ORVM": "Yes  ", "Rear Defogger": "Yes  ", "Exterior Door Handles": "Body Coloured  ", "Rain-sensing Wipers": "Yes  ", "Interior Door Handles": "Chrome  ", "Door Blinds": "Rear - electric  ", "Boot-lid Opener": "Internal with Remote  ", "Rear Window Blind": "Electric  ", "Outside Rear View Mirrors (ORVMs)": "Body Coloured  "}, "Exterior": {"Sunroof / Moonroof": "Panoramic Sunroof  ", "Roof Mounted Antenna": "Yes  ", "Body-Coloured  Bumpers ": "Yes  ", "Chrome Finish Exhaust pipe": "Yes  "}, "Lighting": {"Headlights": "LED  ", "Automatic Head Lamps": "Yes  ", "Follow me home headlamps": "Yes  ", "Fog Lamps": "Front & Rear  ", "Tail Lights": "LED  ", "Cabin Lamps": "Front  ", "Headlight Height Adjuster": "Yes  ", "Glove Box Lamp": "Yes  ", "Lights on Vanity Mirrors": "Driver & Co-Driver  ", "Rear Reading Lamp": "Yes  ", "Cornering Headlights": "Active  "}, "Instrumentation": {"Instrument Cluster": "Digital  ", "Trip Meter": "2 Trips  ", "Average Fuel Consumption": "Yes  ", "Average Speed": "Yes  ", "Distance to Empty": "Yes  ", "Clock": "Digital  ", "Low Fuel Level Warning": "Yes  ", "Door Ajar Warning": "Yes  ", "Adjustable Cluster Brightness": "Yes  ", "Gear Indicator": "Yes  ", "Shift Indicator": "Yes  ", "Heads Up Display (HUD)": "Yes  ", "Tachometer": "Digital  ", "Instantaneous Consumption": "Yes  "}, "Entertainment, Information & Communication": {"Integrated (in-dash) Music System": "Yes  ", "Head Unit Size": "2 Din  ", "Display": "Touch-screen Display  ", "GPS Navigation System": "Yes  ", "Speakers": "6+  ", "USB Compatibility": "Yes  ", "Aux Compatibility": "Yes  ", "Bluetooth Compatibility": "Phone & Audio Streaming  ", "MP3 Playback": "Yes  ", "CD Player": "Yes  ", "AM/FM Radio": "Yes  ", "iPod Compatibility": "Yes  ", "Steering mounted controls": "Yes  ", "Voice Command": "Yes  "}, "Manufacturer Warranty": {"Warranty (Years)": "3  ", "Warranty (Kilometres)": "Unlimited  "}}}}}, "grancabrio": {"gen": {"Price": "Rs. 2.68 Crores onwards", "Mileage": " 6.89 kmpl", "Engine": " 4691 cc", "Transmission": " Automatic", "FuelType": " Petrol"}, "detail": {"4.7 V8 ": {"key Specifications": {"Price": "Rs. 2.68 Crores", "Mileage": " 6.89 kmpl", "Engine": " 4691 cc", "Transmission": " Automatic", "FuelType": " Petrol"}, "spec": {"Engine & Transmission": {"Engine": "4691cc, 8 Cylinders In V Shape, 4 Valves/Cylinder, DOHC ", "Engine Type": "M139S ", "Fuel Type ": "Petrol ", "Max Power (bhp@rpm)": "450 bhp @ 7000 rpm ", "Max Torque (Nm@rpm)": "510 Nm @ 4750 rpm ", "Mileage (ARAI)": "6.89 kmpl", "Drivetrain": "RWD ", "Transmission": "Automatic - 6 Gears, Dual Clutch, Conventional + Paddle Shift, Sport Mode ", "Turbocharger / Supercharger": "Yes, Variable Geometry ", "Others": "Engine Start-Stop Function "}, "Dimensions & Weight": {"Length": "4881 mm", "Width": "1915 mm", "Height": "1353 mm", "Wheelbase": "2942 mm", "Kerb Weight": "1980 kg"}, "Capacity": {"Doors": "2 Doors", "Seating Capacity": "4 Person", "No of Seating Rows": "2 Rows", "Bootspace": "173 litres", "Fuel Tank Capacity": "75 litres"}, "Suspensions, Brakes & Steering ": {"Suspension Front": "double wishbone suspension with forged aluminium arms & hubs ", "Suspension Rear": "double wishbone suspension with forged aluminium arms & hubs ", "Front Brake Type": "Disc ", "Rear Brake Type": "Disc ", "Minimum Turning Radius": "5.35 metres", "Steering Type": "Power assisted (Electric) ", "Wheels": "Alloy Wheels ", "Spare Wheel": "Alloy ", "Front Tyres": "\r\n\t\t\t\t\t\t\t\t\t\t\t\t\t\t\t\t\t245 / 35 R20 \r\n\t\t\t\t\t\t\t\t\t\t\t\t\t\t\t\t\t\t View all tyres\n", "Rear Tyres": "285 / 35 R20 "}}, "fea": {"Safety": {"Airbags": "4 (Driver, Co-Driver & Rear Passengers)  ", "Dual-Stage Airbags": "Yes  ", "Middle Rear Head Rest": "Yes  ", "Child Seat Anchor Points": "Yes  ", "Seat Belt Warning": "Yes  "}, "Braking & Traction": {"Anti-Lock Braking System (ABS)": "Yes  ", "Electronic Brake-force Distribution (EBD)": "Yes  ", "Brake Assist (BA)": "Yes  ", "Electronic Stability Program (ESP)": "Yes  ", "Hill Hold Control": "Yes  ", "Traction Control System (TC/TCS)": "Yes  ", "Ride Height Adjustment": "Yes  ", "Hill Descent Control": "Yes  ", "Limited Slip Differential (LSD)": "Yes  ", "Differential Lock": "Electronic  "}, "Locks & Security": {"Engine immobilizer": "Yes  ", "Central Locking": "Remote  ", "Speed Sensing Door Lock": "Yes  ", "Child Safety Lock": "Yes  "}, "Comfort & Convenience": {"Air Conditioner": "Automatic Climate Control  ", "12V Power Outlets": "Yes  ", "Steering Adjustment": "Tilt & Telescopic  ", "Headlight off and lgnition Key Off Reminder": "Yes  ", "Cruise Control": "Yes  ", "Parking Sensors": "Front & Rear  ", "Parking Assist": "Reverse Camera with Guidance  ", "Anti-glare Mirrors": "Electronic - Internal & Driver  ", "Heater": "Yes  "}, "Seats & Upholstery": {"Seat Upholstery": "Leather  ", "Leather-wrapped Steering Wheel": "Yes  ", "Leather-wrapped Gear Knob": "Yes  ", "Driver Seat Adjustment": "Electrically Adjustable with Memory Function  ", "Front Passenger Seat Adjustment": "Electrically Adjustable with Memory Function  ", "Lumbar Support": "Driver & Co-Driver  ", "Adjustable Lumbar Support": "Electric - 2 way  ", "Driver Armrest": "Yes  ", "Rear Passenger Seats": "Bench  ", "Rear Passenger Adjustable seats": "Electrically Adjustable with Memory Function  ", "3rd Row Seats": "Bench  ", "Ventilated Seats": "Driver only  ", "Interiors": "Single Tone  ", "Rear Armrest": "Yes  ", "Folding Rear Seat": "Full  ", "Split Rear Seat": "60:40 split  ", "Front Seat Pockets": "Yes  ", "Adjustable Head-rests": "Front & Rear  ", "Head-rests": "Front & Rear  "}, "Storage": {"Cup Holders": "Front & Rear  ", "Driver Armrest Storage": "Yes  ", "Cooled Glove Box ": "Yes  ", "Sunglass Holder": "Yes  "}, "Doors, Windows, Mirrors & Wipers": {"Power Windows": "Front Only  ", "One Touch -Down": "All  ", "One Touch - Up": "All  ", "Adjustable ORVM": "Electrically Adjustable & Retractable  ", "Turn Indicators on ORVM": "Yes  ", "Rear Defogger": "Yes  ", "Exterior Door Handles": "Body Coloured  ", "Rain-sensing Wipers": "Yes  ", "Interior Door Handles": "Chrome  ", "Door Blinds": "Front and Rear Electric  ", "Boot-lid Opener": "Internal with Remote  ", "Rear Window Blind": "Electric  ", "Outside Rear View Mirrors (ORVMs)": "Body Coloured  "}, "Exterior": {"Roof Mounted Antenna": "Yes  ", "Body-Coloured  Bumpers ": "Yes  "}, "Lighting": {"Headlights": "LED  ", "Automatic Head Lamps": "Yes  ", "Follow me home headlamps": "Yes  ", "Fog Lamps": "Front & Rear  ", "Tail Lights": "LED  ", "Cabin Lamps": "Front  ", "Headlight Height Adjuster": "Yes  ", "Glove Box Lamp": "Yes  ", "Lights on Vanity Mirrors": "Driver & Co-Driver  ", "Rear Reading Lamp": "Yes  ", "Cornering Headlights": "Active  "}, "Instrumentation": {"Instrument Cluster": "Digital  ", "Trip Meter": "2 Trips  ", "Average Fuel Consumption": "Yes  ", "Average Speed": "Yes  ", "Distance to Empty": "Yes  ", "Clock": "Digital  ", "Low Fuel Level Warning": "Yes  ", "Door Ajar Warning": "Yes  ", "Adjustable Cluster Brightness": "Yes  ", "Gear Indicator": "Yes  ", "Shift Indicator": "Yes  ", "Heads Up Display (HUD)": "Yes  ", "Tachometer": "Digital  "}, "Entertainment, Information & Communication": {"Integrated (in-dash) Music System": "Yes  ", "Head Unit Size": "2 Din  ", "Display": "Touch-screen Display  ", "Display Screen for Rear Passengers": "Yes  ", "GPS Navigation System": "Yes  ", "Speakers": "6+  ", "USB Compatibility": "Yes  ", "Aux Compatibility": "Yes  ", "Bluetooth Compatibility": "Phone  ", "MP3 Playback": "Yes  ", "CD Player": "Yes  ", "AM/FM Radio": "Yes  ", "iPod Compatibility": "Yes  ", "Steering mounted controls": "Yes  ", "Voice Command": "Yes  "}, "Manufacturer Warranty": {"Warranty (Years)": "3  ", "Warranty (Kilometres)": "Unlimited  "}}}}}}
